Workbook

Sheet Cover
B2: GridMats Solar × Reliance
B3: Cost-benefit model for solar-park roads and solar walkways, with a pilot offer
B4: Prepared for Reliance Industries Ltd (Reliance New Energy) by GroundReality Enterprises Pvt Ltd (GridMats), October 2026
B6: Scenario shown | C6: =Scenario -> Base | D6: Change it on the Inputs sheet (cell C3)
B8: Headline results
B9: Measure | C9: Value | E9: Where
B10: Solar-park roads, per 100 MW block
B11: NPV to Reliance over 25 years (₹ Cr) | C11: =Park_NPV -> 4.0949028 | E11: Solar Park 100MW
B12: Up-front GridMats premium (₹ Cr) | C12: =Park_Premium -> 3.459285 | E12: Solar Park 100MW
B13: Premium as % of solar plant capex | C13: =Park_PremPct -> 0.0086482125 | E13: Solar Park 100MW
B14: IRR on the premium | C14: =Park_IRR -> 0.20861507 | E14: Solar Park 100MW
B15: Simple payback (years) | C15: =Park_Payback -> 4.6793249 | E15: Solar Park 100MW
B16: NPV, conservative case (₹ Cr) | C16: =Scn_Cons -> 3.3013491 | E16: Sensitivity
B17: NPV, optimistic case (₹ Cr) | C17: =Scn_Opt -> 7.6615724 | E17: Sensitivity
B18: 25-year cost per m²
B19: O&M tracks: GridMats S2 saving vs WBM | C19: =SavePct_S2_WBM -> 0.064264722 | E19: Road LCC
B20: Main roads: GridMats S1 saving vs bituminous | C20: =SavePct_S1_BT -> 0.30046021 | E20: Road LCC
B21: Main roads: GridMats S1 saving vs concrete | C21: =SavePct_S1_PQC -> 0.33412917 | E21: Road LCC
B22: GridMats Solar Walkway, per m²
B23: Pilot site | C23: =Site -> Navi Mumbai | E23: Inputs
B24: Year-1 electricity bill saved (₹ / m²) | C24: =Wk_Save1 -> 2208 | E24: Solar Walkway
B25: Simple payback (years) | C25: =Wk_Payback -> 5.3495034 | E25: Solar Walkway
B26: IRR after tax with accelerated depreciation | C26: =Wk_IRRAT -> 0.17026592 | E26: Solar Walkway
B27: Pilot offer
B28: Reliance pays GridMats (ex-GST) | C28: =Pilot_Pays -> 5534220 | E28: Pilot Offer
B29: GridMats contribution (value given) | C29: =Pilot_Contrib -> 1316000 | E29: Pilot Offer
B30: Grid price reduction vs the 2025 Kutch trial | C30: =Pilot_vsTrial -> 0.22746781 | E30: Pilot Offer
B31: Sustainability per 100 MW block
B32: Recycled PP put to use (t) | C32: =Sus_PP -> 326.7 | E32: Sustainability
B33: CO2e avoided over 25 years (t) | C33: =Sus_CO2 -> 10873.01 | E33: Sustainability
B35: How to read this model
B36: 1. Blue cells are inputs, yellow-filled blue cells are key assumptions, black cells are formulas, green cells link to other sheets.
B37: 2. All money is in Indian rupees, excluding GST, at 2026 prices, escalated and discounted as set on the Inputs sheet.
B38: 3. The road comparison uses one solar block (default 100 MWp) with 10 km of internal road: 30% main roads (GridMats S1 instead of bituminous or concrete) and 70% O&M tracks (GridMats S2 instead of WBM).
B39: 4. GridMats costs more than WBM on day one. The model shows where that premium is earned back: avoided regrading and regravelling, less dust on modules, and carbon.
B40: 5. The GridMats Solar Walkway is at pilot stage. Its yield, life and upkeep are assumptions; the pilot measures them.
B41: 6. Sources are listed on the Sources sheet and next to every input.

Sheet Inputs
A1: Inputs and assumptions
A2: Blue = input you can change · yellow fill = key assumption · black = formula. All money ex-GST, 2026 prices.
A3: Scenario used across the model | C3: Base | D3: ← choose Conservative, Base or Optimistic
A4: Scenario index | C4: =MATCH(C3,$D$6:$F$6,0) -> 2
A6: Assumption | B6: Unit | C6: Value used | D6: Conservative | E6: Base | F6: Optimistic | G6: Source / basis
A8: 1. General
A9: Discount rate (nominal, pre-tax) | B9: % | C9: 0.1 | G9: Assumption: indicative large-corporate cost of capital. Sensitivity sheet shows 8% and 12%.
A10: Escalation of civil and upkeep costs | B10: % / yr | C10: 0.05 | G10: Assumption (close to Indian CPI).
A11: Corporate income-tax rate | B11: % | C11: 0.2517 | G11: Section 115BAA rate incl. surcharge and cess. Used only in the walkway after-tax view.
A12: Carbon value | B12: ₹ / t CO2e | C12: =INDEX(D12:F12,ScnIdx) -> 700 | D12: 400 | E12: 700 | F12: 1500 | G12: India CCTS: first carbon credit certificate trades expected around Oct 2026; expected ₹250-1,500/t, scenario studies ₹400-900/t (reclimatize.in, 2026).
A13: Carbon value escalation | B13: % / yr | C13: 0.05 | G13: Assumption.
A14: India grid emission factor | B14: t CO2 / MWh | C14: 0.71 | G14: CEA CO2 Baseline Database v21.0 (FY2024-25), weighted average.
A16: 2. Solar park block (Kutch region)
A17: Solar block size used for comparison | B17: MWp | C17: 100 | G17: Basis of comparison.
A18: Solar plant capex (for context only) | B18: ₹ Cr / MW | C18: 4 | G18: Utility-scale benchmark ₹3.5-4.5 Cr/MW (greentechlead, 2026).
A19: Specific yield, Kutch region | B19: kWh / kWp / yr | C19: 1870 | G19: Gujarat plant 1,872 kWh/kWp at 21.3% CUF; Kutch plane-of-array irradiance 2,100-2,350 kWh/m²/yr.
A20: Module degradation | B20: % / yr | C20: 0.004 | G20: TOPCon datasheets 0.4%/yr after year 1; Reliance HJT 0.3%/yr (company claim).
A21: Value of each extra kWh generated | B21: ₹ / kWh | C21: =INDEX(D21:F21,ScnIdx) -> 2.7 | D21: 2.55 | E21: 2.7 | F21: 2.9 | G21: Solar PPA ₹2.52-2.61 (NHPC/NTPC); solar + storage ₹2.86-2.87 (SECI ISTS-XX, Oct 2025). Conservative: captive value to Reliance is higher.
A22: Energy value escalation | B22: % / yr | C22: 0 | G22: Flat, PPA-style.
A23: Internal road per 100 MW | B23: km | C23: 10 | G23: GridMats solar and wind parks flier: 8-12 km per 100 MW. Independent estimate 0.1-0.2 km/MW.
A24: Share of road length that is main / spine / inverter-yard road | B24: % | C24: 0.3 | G24: Assumption.
A25: Main road width | B25: m | C25: 6 | G25: GridMats per-km park rate covers 5-7 m roads; Pavagada DPR uses 8.5 m and 4.5 m.
A26: O&M track width | B26: m | C26: 4.5 | G26: Pavagada DPR 4.5 m; NTPC tenders 3.75 m WBM.
A27: Conventional main-road surface it replaces | B27: choice | C27: Bituminous | G27: Choose Bituminous (default, conservative) or PQC. O&M tracks are compared with WBM / gravel.
A28: Average yearly energy lost to module soiling, with routine cleaning | B28: % of yield | C28: 0.03 | G28: West-India dry-season soiling 0.3-0.5%/day (Gandhinagar 0.37%/day); pv-magazine India uses a 3% example (Apr 2026). Assumption.
A29: Share of that soiling caused by traffic dust from unpaved O&M tracks | B29: % | C29: =INDEX(D29:F29,ScnIdx) -> 0.15 | D29: 0.1 | E29: 0.15 | F29: 0.25 | G29: Assumption. Univ. of Johannesburg (2025) measured PV soiling highest next to a gravel road, falling with distance. The pilot measures this.
A30: Dust cut by GridMats S2 (graded chips confined in cells) vs WBM | B30: % | C30: 0.7 | G30: Assumption: 8-12 mm graded chips, no fines, held in cells. Pilot KPI.
A31: Module cleaning cost | B31: ₹ lakh / MW / yr | C31: 1.5 | G31: Robotic about ₹1 lakh/MW/yr; manual up to ₹7.5 lakh/MW/yr (Renewable Watch, 2023).
A32: Cleaning cost avoided through fewer cycles | B32: % | C32: =INDEX(D32:F32,ScnIdx) -> 0 | D32: 0 | E32: 0 | F32: 0.05 | G32: Optimistic case only, so it is not double-counted with the energy gain.
A33: Earlier energisation from all-weather access | B33: days | C33: =INDEX(D33:F33,ScnIdx) -> 0 | D33: 0 | E33: 0 | F33: 2 | G33: Optimistic case only.
A34: Years of heavy construction traffic needing dust suppression | B34: years | C34: 2 | G34: Assumption.
A35: Dust suppression on WBM (water tanker + water) | B35: ₹ / m² / yr | C35: 75 | G35: Assumption: about ₹4,000 a day per tanker covering ~13,500 m², 250 days a year.
A36: Sprinkling water on WBM | B36: L / m² / day | C36: 1 | G36: Assumption.
A37: Sprinkling days per year | B37: days | C37: 200 | G37: Assumption.
A38: Annual rainfall, Kutch / Patan | B38: mm | C38: 400 | G38: Assumption: Kutch district normal about 350-450 mm.
A39: Share of rain returned to ground on permeable S2 | B39: % | C39: 0.9 | G39: GridMats Design Engine factor.
A41: 3. Conventional surfaces, build cost (₹ / m², ex-GST)
A42: WBM / gravel road (GSB 150 + WBM 150) | B42: ₹ / m² | C42: 600 | G42: Tamil Nadu G.O. (2021-22) single-layer WBM ₹21.99 lakh/km, about ₹590/m²; GridMats sales pitch ₹250-500/m² (surface only).
A43: Bituminous road, IRC:37 | B43: ₹ / m² | C43: 2000 | G43: CPWD DSR 2023 internal road (GSB 225 + WBM 200 + BM 50 + BC 40) about ₹2,050/m²; GridMats pitch ₹1,500-1,900/m².
A44: Concrete road, IRC:58 (PQC + DLC) | B44: ₹ / m² | C44: 3200 | G44: GridMats pitch ₹2,900-3,200/m²; Design Engine 73 (280 mm PQC) ₹3,561/m²; CPWD-derived ₹4,020/m².
A45: Paver-block walkway (avoided by a solar walkway) | B45: ₹ / m² | C45: 1100 | G45: Paver blocks 60-80 mm ₹900-1,300/m² (GridMats pitch); ₹548-1,374/m² (Infralens, 2026).
A47: 4. Upkeep (today's ₹ / m², escalated in the model)
A48: WBM: post-monsoon regrading, rut and pothole fill | B48: ₹ / m² / yr | C48: 40 | G48: Assumption (about ₹1.8 lakh/km/yr on a 4.5 m track). GridMats pitch: 'regrade every monsoon'.
A49: WBM: regravelling | B49: ₹ / m² / event | C49: 250 | G49: Assumption, about 40% of build cost.
A50: WBM: regravelling interval | B50: years | C50: 4 | G50: Regravelling every 4-7 years (TRL / World Bank road-cost data).
A51: Bituminous: routine maintenance | B51: ₹ / m² / yr | C51: 20 | G51: IRC:82 routine maintenance ₹0.5-1.5 lakh/km/yr.
A52: Bituminous: 40 mm BC renewal | B52: ₹ / m² / event | C52: 450 | G52: Assumption.
A53: Bituminous: renewal interval | B53: years | C53: 5 | G53: IRC:82 renewal every 4-6 years; GridMats pitch 3-5 years.
A54: Concrete: routine maintenance | B54: ₹ / m² / yr | C54: 10 | G54: Assumption.
A55: Concrete: joint reseal, grinding, slab repairs | B55: ₹ / m² / event | C55: 150 | G55: Design Engine 73 lifecycle (repairs at years 10, 20, 30).
A56: Concrete: repair interval | B56: years | C56: 10 | G56: Design Engine 73 lifecycle.
A57: GridMats: routine upkeep | B57: % of build cost / yr | C57: 0.005 | G57: Design Engine 73 lifecycle method (0.5% a year).
A58: GridMats S1: chip-and-cement top-up | B58: ₹ / m² / event | C58: 150 | G58: GridMats SOP: top-up at years 10, 20, 30.
A59: GridMats S1: top-up interval | B59: years | C59: 10 | G59: GridMats SOP.
... A61: GridMats S2: chip top-up interval | B61: years | C61: 3 | G61: Assumption (top-up visit at 6 months is included in the build).
A63: 5. GridMats rates and factors
A64: GridMats OC-HD 40, park / annual-contract rate | B64: ₹ / m² | C64: 900 | G64: GridMats price ladder (25 Sep 2026): ₹900/m² above 25,000 m² or on a 12-month rate contract; ₹935 at 5,000-25,000 m².
A65: GridMats OC-LW 40, annual rate | B65: ₹ / m² | C65: 550 | G65: GridMats price ladder (25 Sep 2026).
A66: GridMats OC-LW 40, under 1,000 m² | B66: ₹ / m² | C66: 690 | G66: GridMats price ladder (25 Sep 2026).
A67: Geotextile, 200 gsm non-woven | B67: ₹ / m² | C67: 55 | G67: As supplied to Reliance in 2025.
A68: Freight, factory to Kutch site | B68: ₹ / m² | C68: 60 | G68: Design Engine BoQ indicative; at cost.
A69: Grid laying labour | B69: ₹ / m² | C69: 60 | G69: Design Engine 73 BoQ.
A70: U-nail (8 mm bar) | B70: ₹ each | C70: 8 | G70: Design Engine 73 BoQ.
A71: U-nails per m² on roads | B71: nos / m² | C71: 0.4 | G71: GridMats SOP: one per 2-3 m² on roads and slopes.
A72: Subgrade preparation | B72: ₹ / m² | C72: 60 | G72: Design Engine 73 BoQ (Bengaluru 2026 rates).
A73: GSB (MoRTH 401) | B73: ₹ / m³ | C73: 1400 | G73: Design Engine 73 BoQ.
A74: Open-graded GSB | B74: ₹ / m³ | C74: 1600 | G74: Design Engine 73 BoQ.
A75: WMM (MoRTH 406) | B75: ₹ / m³ | C75: 1900 | G75: Design Engine 73 BoQ.
... A92: Binder in a 40 mm BC renewal | B92: kg / m² | C92: 4.7 | G92: Derived: about 5% binder by weight.
A94: 6. GridMats Solar Walkway (pre-commercial: the pilot measures these)
A95: Walkway pilot site | B95: choice | C95: Navi Mumbai | G95: Navi Mumbai = Reliance Corporate Park (higher power cost, most visible). Jamnagar = Giga Complex. Both are shown on the Solar Walkway sheet.
A96: Rated power of the walkway | B96: W / m² | C96: 160 | G96: GridMats Solar Walkway flier (6 Oct 2026): 40 W per module, one on each grid, 4 grids per m².
A97: Yield, flat walk-on modules, Jamnagar | B97: kWh / kWp / yr | C97: 1300 | G97: Assumption: about 20% below a tilted Gujarat rooftop (~1,650) for flat mounting, heat and foot-traffic soiling.
A98: Yield, flat walk-on modules, Navi Mumbai | B98: kWh / kWp / yr | C98: 1150 | G98: Assumption: Mumbai rooftop 1,420-1,520 kWh/kWp, derated about 20%.
A99: Yield scenario multiplier | B99: × | C99: =INDEX(D99:F99,ScnIdx) -> 1 | D99: 0.9 | E99: 1 | F99: 1.1 | G99: Scenario range on the yield above.
A100: Grid power cost avoided, Jamnagar (HT, landed) | B100: ₹ / kWh | C100: 7.5 | G100: GERC FY27: HT energy charge ₹4.30/kWh plus fuel surcharge and duty; landed about ₹7.5-8.5 (estimate).
A101: Grid power cost avoided, Navi Mumbai (HT commercial, landed) | B101: ₹ / kWh | C101: 12 | G101: MERC FY27: HT-II commercial ₹13.72/kVAh; HT-I industrial ₹8.44/kVAh.
A102: Power tariff escalation | B102: % / yr | C102: 0.03 | G102: Assumption.
A103: Walkway module degradation | B103: % / yr | C103: 0.007 | G103: Assumption (higher than ground-mount for walk-on use).
A104: Walkway module life | B104: years | C104: 20 | G104: Assumption; the pilot validates durability.
A105: Walkable PV layer (modules + MLP lumber with wiring) | B105: ₹ / m² | C105: 9500 | G105: GridMats Solar pilot quote, Oct 2026: walkable module about ₹9,500/m².
A106: Inverter, cabling, protection, metering | B106: ₹ / kWp | C106: 12500 | G106: Assumption.
A107: Walkway cleaning and inspection | B107: ₹ / m² / yr | C107: 150 | G107: Assumption.
A108: Inverter replacement | B108: ₹ / kWp | C108: 4000 | G108: Assumption.
A109: Inverter replacement year | B109: year | C109: 12 | G109: Assumption.
A110: Accelerated depreciation on solar (WDV) | B110: % | C110: 0.4 | G110: Income-tax Act: 40% WDV for solar plant.
A111: Benchmark: C&I rooftop solar | B111: ₹ / kWp | C111: 40000 | G111: C&I rooftop turnkey ₹36-44/Wp (2026).
A112: Benchmark: solar carport | B112: ₹ / kWp | C112: 50000 | G112: Commercial carports ₹40,000-60,000/kW (2026).
A114: 7. Pilot (Reliance)
A115: Pilot main road, GridMats S1 | B115: km | C115: 0.4 | G115: Proposed pilot scope.
A116: Pilot O&M track, GridMats S2 | B116: km | C116: 0.6 | G116: Proposed pilot scope.
A117: Pilot GridMats Solar Walkway | B117: m² | C117: 50 | G117: Proposed pilot scope.
A118: List price OC-HD 40 at pilot size (5,000-25,000 m²) | B118: ₹ / m² | C118: 935 | G118: GridMats price ladder (25 Sep 2026).
A119: Pilot offer price OC-HD 40 | B119: ₹ / m² | C119: 900 | G119: Proposed: annual-contract rate at pilot size.
A120: OC-HD 40 price on the 2025 Kutch trial | B120: ₹ / m² | C120: 1165 | G120: Reliance PO, Sep 2025.
A121: Grid laid per crew-day | B121: m² / day | C121: 350 | G121: GridMats systems manual: 300-400 m² per crew of four.
A122: Supervisor man-day rate | B122: ₹ / day | C122: 15000 | G122: GridMats standard rate.
A123: Supervisor travel and stay for the full build | B123: ₹ | C123: 75000 | G123: Estimate; normally paid by the client.
A124: Site design (IITPAVE on site CBR), BoQ, method statement, hold-point QC | B124: ₹ | C124: 150000 | G124: Estimate of value; included.
A125: IoT sensors + live dashboard + soiling study + 6/12-month reports | B125: ₹ | C125: 400000 | G125: Estimate of value; offered free.
...

Sheet Unit Rates
A1: Unit rates: build-up of installed cost (₹ / m², ex-GST)
A2: GridMats sections follow the GridMats base tables for Kutch's low-CBR (2-5%) saline ground. Blue quantities can be edited.
A4: GridMats S1: cement-treated gravel, main / spine roads and inverter yards (load class D, CBR 2-5%)
A5: Item | B5: Quantity / m² | C5: Unit | D5: Rate (₹) | E5: ₹ / m² | F5: Basis
A6: Subgrade preparation | B6: 1 | C6: m² | D6: =SubgradeRate -> 60 | E6: =B6*D6 -> 60 | F6: Compact to 98% MDD
A7: GSB 200 mm | B7: 0.2 | C7: m³ | D7: =GSBRate -> 1400 | E7: =B7*D7 -> 280 | F7: Base table, load class D, CBR 2-5%
A8: WMM 150 mm | B8: 0.15 | C8: m³ | D8: =WMMRate -> 1900 | E8: =B8*D8 -> 285 | F8: Base table, load class D
A9: Bedding 25 mm M-sand / crusher dust | B9: 0.025 | C9: m³ | D9: =SandRate -> 1800 | E9: =B9*D9 -> 45
A10: Geotextile 200 gsm | B10: 1 | C10: m² | D10: =Geotex -> 55 | E10: =B10*D10 -> 55 | F10: Separator on saline formation
A11: GridMats OC-HD 40 | B11: 1 | C11: m² | D11: =GridHD -> 900 | E11: =B11*D11 -> 900 | F11: Park / annual-contract rate
A12: Freight to site | B12: 1 | C12: m² | D12: =Freight -> 60 | E12: =B12*D12 -> 60 | F12: At cost
A13: Grid laying labour | B13: 1 | C13: m² | D13: =LayLab -> 60 | E13: =B13*D13 -> 60 | F13: Built by teams GridMats trains
A14: U-nails | B14: =NailDensity -> 0.4 | C14: nos | D14: =NailPrice -> 8 | E14: =B14*D14 -> 3.2 | F14: 1 per 2-3 m²
A15: Cement-treated gravel infill | B15: 1 | C15: m² | D15: =CTGInfill -> 253 | E15: =B15*D15 -> 253 | F15: Opens to trucks at 7 days (7-day cubes 2 MPa)
A16: Edges and drains | B16: 1 | C16: m² | D16: =S1Edges -> 28 | E16: =B16*D16 -> 28
A17: Installed cost | E17: =SUM(E6:E16) -> 2029.2 | F17: Compare: GridMats indicative ₹1,400-1,900/m²; Design Engine 73 internal road ₹2,011/m².
A19: GridMats S2: permeable stone chip, O&M tracks (load class C, CBR 2-5%) - as built at Kutch in 2025
A20: Item | B20: Quantity / m² | C20: Unit | D20: Rate (₹) | E20: ₹ / m² | F20: Basis
A21: Subgrade preparation | B21: 1 | C21: m² | D21: =SubgradeRate -> 60 | E21: =B21*D21 -> 60
A22: GSB 100 mm | B22: 0.1 | C22: m³ | D22: =GSBRate -> 1400 | E22: =B22*D22 -> 140 | F22: Base table, load class C, CBR 2-5%
A23: WMM 150 mm | B23: 0.15 | C23: m³ | D23: =WMMRate -> 1900 | E23: =B23*D23 -> 285 | F23: Base table, load class C
A24: Bedding 20 mm | B24: 0.02 | C24: m³ | D24: =SandRate -> 1800 | E24: =B24*D24 -> 36
A25: Geotextile 200 gsm | B25: 1 | C25: m² | D25: =Geotex -> 55 | E25: =B25*D25 -> 55
A26: GridMats OC-HD 40 | B26: 1 | C26: m² | D26: =GridHD -> 900 | E26: =B26*D26 -> 900 | F26: Park / annual-contract rate
A27: Freight to site | B27: 1 | C27: m² | D27: =Freight -> 60 | E27: =B27*D27 -> 60 | F27: At cost
A28: Grid laying labour | B28: 1 | C28: m² | D28: =LayLab -> 60 | E28: =B28*D28 -> 60
A29: U-nails | B29: =NailDensity -> 0.4 | C29: nos | D29: =NailPrice -> 8 | E29: =B29*D29 -> 3.2
A30: 8-12 mm stone-chip infill (about 37 L/m²) | B30: 0.037 | C30: m³ | D30: =ChipRate -> 1900 | E30: =B30*D30 -> 70.3 | F30: Opens the same day it is filled
A31: Edges | B31: 1 | C31: m² | D31: =S2Edges -> 12 | E31: =B31*D31 -> 12
A32: Installed cost | E32: =SUM(E21:E31) -> 1681.5 | F32: Compare: GridMats recorded S2 range ₹1,434-1,866/m².
A33: Variant: S2 with lighter OC-LW 40 (cars and LCVs only) | E33: =S2_Capex-GridHD+GridLW -> 1331.5 | F33: For tracks without trucks or water tankers. Not used in the base case.
A36: GridMats Solar Walkway: base and PV layer (per m² of walkway)
A37: Item | B37: Quantity / m² | C37: Unit | D37: Rate (₹) | E37: ₹ / m² | F37: Basis
A38: Subgrade preparation | B38: 1 | C38: m² | D38: =SubgradeRate -> 60 | E38: =B38*D38 -> 60
A39: Open-graded GSB 100 mm | B39: 0.1 | C39: m³ | D39: =OGSBRate -> 1600 | E39: =B39*D39 -> 160 | F39: Drains through
A40: Bedding 20 mm | B40: 0.02 | C40: m³ | D40: =SandRate -> 1800 | E40: =B40*D40 -> 36
A41: GridMats OC-LW 40 (500 × 500 mm, 4 per m²) | B41: 1 | C41: m² | D41: =GridLWSmall -> 690 | E41: =B41*D41 -> 690 | F41: Under-1,000 m² price
A42: Freight | B42: 1 | C42: m² | D42: =Freight -> 60 | E42: =B42*D42 -> 60
A43: Grid laying labour | B43: 1 | C43: m² | D43: =LayLab -> 60 | E43: =B43*D43 -> 60
A44: Edges | B44: 1 | C44: m² | D44: =S2Edges -> 12 | E44: =B44*D44 -> 12
A45: Installed cost | E45: =SUM(E38:E44) -> 1078 | F45: GridMats structural base of the walkway.
A46: Walkable PV layer (modules + MLP lumber carrying the wiring) | E46: =SolarLayer -> 9500
A47: Inverter, cabling, protection, metering | E47: =BOS*PowerDens/1000 -> 2000 | F47: ₹/kWp × kWp per m²
A48: Solar walkway, installed | E48: =WkBase+E46+E47 -> 12578
A49: Cost of the solar part per kWp | E49: =(SolarLayer+BOS*PowerDens/1000)/(PowerDens/1000) -> 71875 | F49: Compare: C&I rooftop ₹40,000/kWp; solar carport ₹40,000-60,000/kWp.
A52: Conventional surfaces (from Inputs)
A53: Surface | E53: ₹ / m² | F53: Typical section
A54: WBM / gravel road | E54: =WBM_Capex -> 600 | F54: GSB 150 + WBM 150; regrade every monsoon
A55: Bituminous road, IRC:37 | E55: =BT_Capex -> 2000 | F55: GSB 225 + WBM 200 + BM 50 + BC 40
A56: Concrete road, IRC:58 | E56: =PQC_Capex -> 3200 | F56: PQC 220 + DLC 150 (+ GSB); 14-28 days to open
A57: Paver-block walkway | E57: =Paver_Capex -> 1100 | F57: 60-80 mm pavers on sand

Sheet Road LCC
A1: Road life-cycle cost per m² over 25 years
A2: ₹ per m², nominal, escalated at the cost-escalation rate and discounted at the discount rate. Year 0 = build.
A5: Year | C5: 0 | D5: 1 | E5: 2 | F5: 3 | G5: 4 | H5: 5 | I5: 6 | J5: 7 | K5: 8 | L5: 9 | M5: 10 | N5: 11 | O5: 12 | P5: 13 | Q5: 14 | R5: 15 | S5: 16 | T5: 17 | U5: 18 | V5: 19 | W5: 20 | X5: 21 | Y5: 22 | Z5: 23 | AA5: 24 | AB5: 25 | AC5: PV
A6: Discount factor | C6: =1/(1+DiscRate)^C$5 -> 1 | D6: =1/(1+DiscRate)^D$5 -> 0.90909091 | E6: =1/(1+DiscRate)^E$5 -> 0.82644628 | F6: =1/(1+DiscRate)^F$5 -> 0.7513148 | G6: =1/(1+DiscRate)^G$5 -> 0.68301346 | H6: =1/(1+DiscRate)^H$5 -> 0.62092132 | I6: =1/(1+DiscRate)^I$5 -> 0.56447393 | J6: =1/(1+DiscRate)^J$5 -> 0.51315812 | ... AB6: =1/(1+DiscRate)^AB$5 -> 0.092295998
A7: Cost index | C7: =(1+CostEsc)^C$5 -> 1 | D7: =(1+CostEsc)^D$5 -> 1.05 | E7: =(1+CostEsc)^E$5 -> 1.1025 | F7: =(1+CostEsc)^F$5 -> 1.157625 | G7: =(1+CostEsc)^G$5 -> 1.2155063 | H7: =(1+CostEsc)^H$5 -> 1.2762816 | I7: =(1+CostEsc)^I$5 -> 1.3400956 | J7: =(1+CostEsc)^J$5 -> 1.4071004 | ... AB7: =(1+CostEsc)^AB$5 -> 3.3863549
A9: WBM / gravel road
A10: Build | C10: =WBM_Capex -> 600 | D10: 0 | E10: 0 | F10: 0 | G10: 0 | H10: 0 | I10: 0 | J10: 0 | K10: 0 | L10: 0 | M10: 0 | N10: 0 | O10: 0 | P10: 0 | Q10: 0 | R10: 0 | S10: 0 | T10: 0 | U10: 0 | V10: 0 | W10: 0 | X10: 0 | Y10: 0 | Z10: 0 | AA10: 0 | AB10: 0 | AC10: =SUMPRODUCT(C10:AB10,C$6:AB$6) -> 600
A11: Routine regrading | C11: 0 | D11: =WBM_Routine*D$7 -> 42 | E11: =WBM_Routine*E$7 -> 44.1 | F11: =WBM_Routine*F$7 -> 46.305 | G11: =WBM_Routine*G$7 -> 48.62025 | H11: =WBM_Routine*H$7 -> 51.051262 | I11: =WBM_Routine*I$7 -> 53.603826 | J11: =WBM_Routine*J$7 -> 56.284017 | K11: =WBM_Routine*K$7 -> 59.098218 | ... AB11: =WBM_Routine*AB$7 -> 135.4542 | AC11: =SUMPRODUCT(C11:AB11,C$6:AB$6) -> 577.46051
A12: Regravelling | C12: 0 | D12: =IF(AND(MOD(D$5,WBM_Cycle)=0,D$5<25),WBM_Regravel*D$7,0) -> 0 | E12: =IF(AND(MOD(E$5,WBM_Cycle)=0,E$5<25),WBM_Regravel*E$7,0) -> 0 | F12: =IF(AND(MOD(F$5,WBM_Cycle)=0,F$5<25),WBM_Regravel*F$7,0) -> 0 | G12: =IF(AND(MOD(G$5,WBM_Cycle)=0,G$5<25),WBM_Regravel*G$7,0) -> 303.87656 | H12: =IF(AND(MOD(H$5,WBM_Cycle)=0,H$5<25),WBM_Regravel*H$7,0) -> 0 | I12: =IF(AND(MOD(I$5,WBM_Cycle)=0,I$5<25),WBM_Regravel*I$7,0) -> 0 | J12: =IF(AND(MOD(J$5,WBM_Cycle)=0,J$5<25),WBM_Regravel*J$7,0) -> 0 | K12: =IF(AND(MOD(K$5,WBM_Cycle)=0,K$5<25),WBM_Regravel*K$7,0) -> 369.36386 | ... AB12: =IF(AND(MOD(AB$5,WBM_Cycle)=0,AB$5<25),WBM_Regravel*AB$7,0) -> 0 | AC12: =SUMPRODUCT(C12:AB12,C$6:AB$6) -> 822.13732
A13: Dust suppression (construction years) | C13: 0 | D13: =IF(D$5<=DustYears,DustCost*D$7,0) -> 78.75 | E13: =IF(E$5<=DustYears,DustCost*E$7,0) -> 82.6875 | F13: =IF(F$5<=DustYears,DustCost*F$7,0) -> 0 | G13: =IF(G$5<=DustYears,DustCost*G$7,0) -> 0 | H13: =IF(H$5<=DustYears,DustCost*H$7,0) -> 0 | I13: =IF(I$5<=DustYears,DustCost*I$7,0) -> 0 | J13: =IF(J$5<=DustYears,DustCost*J$7,0) -> 0 | K13: =IF(K$5<=DustYears,DustCost*K$7,0) -> 0 | ... AB13: =IF(AB$5<=DustYears,DustCost*AB$7,0) -> 0 | AC13: =SUMPRODUCT(C13:AB13,C$6:AB$6) -> 139.92769
A14: Total | C14: =SUM(C10:C13) -> 600 | D14: =SUM(D10:D13) -> 120.75 | E14: =SUM(E10:E13) -> 126.7875 | F14: =SUM(F10:F13) -> 46.305 | G14: =SUM(G10:G13) -> 352.49681 | H14: =SUM(H10:H13) -> 51.051262 | I14: =SUM(I10:I13) -> 53.603826 | J14: =SUM(J10:J13) -> 56.284017 | ... AB14: =SUM(AB10:AB13) -> 135.4542 | AC14: =SUMPRODUCT(C14:AB14,C$6:AB$6) -> 2139.5255
A16: Bituminous road, IRC:37
A17: Build | C17: =BT_Capex -> 2000 | D17: 0 | E17: 0 | F17: 0 | G17: 0 | H17: 0 | I17: 0 | J17: 0 | K17: 0 | L17: 0 | M17: 0 | N17: 0 | O17: 0 | P17: 0 | Q17: 0 | R17: 0 | S17: 0 | T17: 0 | U17: 0 | V17: 0 | W17: 0 | X17: 0 | Y17: 0 | Z17: 0 | AA17: 0 | AB17: 0 | AC17: =SUMPRODUCT(C17:AB17,C$6:AB$6) -> 2000
A18: Routine maintenance | C18: 0 | D18: =BT_Routine*D$7 -> 21 | E18: =BT_Routine*E$7 -> 22.05 | F18: =BT_Routine*F$7 -> 23.1525 | G18: =BT_Routine*G$7 -> 24.310125 | H18: =BT_Routine*H$7 -> 25.525631 | I18: =BT_Routine*I$7 -> 26.801913 | J18: =BT_Routine*J$7 -> 28.142008 | K18: =BT_Routine*K$7 -> 29.549109 | ... AB18: =BT_Routine*AB$7 -> 67.727099 | AC18: =SUMPRODUCT(C18:AB18,C$6:AB$6) -> 288.73026
A19: BC renewal | C19: 0 | D19: =IF(AND(MOD(D$5,BT_Cycle)=0,D$5<25),BT_Overlay*D$7,0) -> 0 | E19: =IF(AND(MOD(E$5,BT_Cycle)=0,E$5<25),BT_Overlay*E$7,0) -> 0 | F19: =IF(AND(MOD(F$5,BT_Cycle)=0,F$5<25),BT_Overlay*F$7,0) -> 0 | G19: =IF(AND(MOD(G$5,BT_Cycle)=0,G$5<25),BT_Overlay*G$7,0) -> 0 | H19: =IF(AND(MOD(H$5,BT_Cycle)=0,H$5<25),BT_Overlay*H$7,0) -> 574.3267 | I19: =IF(AND(MOD(I$5,BT_Cycle)=0,I$5<25),BT_Overlay*I$7,0) -> 0 | J19: =IF(AND(MOD(J$5,BT_Cycle)=0,J$5<25),BT_Overlay*J$7,0) -> 0 | K19: =IF(AND(MOD(K$5,BT_Cycle)=0,K$5<25),BT_Overlay*K$7,0) -> 0 | ... AB19: =IF(AND(MOD(AB$5,BT_Cycle)=0,AB$5<25),BT_Overlay*AB$7,0) -> 0 | AC19: =SUMPRODUCT(C19:AB19,C$6:AB$6) -> 1040.6495
A20: Total | C20: =SUM(C17:C19) -> 2000 | D20: =SUM(D17:D19) -> 21 | E20: =SUM(E17:E19) -> 22.05 | F20: =SUM(F17:F19) -> 23.1525 | G20: =SUM(G17:G19) -> 24.310125 | H20: =SUM(H17:H19) -> 599.85233 | I20: =SUM(I17:I19) -> 26.801913 | J20: =SUM(J17:J19) -> 28.142008 | ... AB20: =SUM(AB17:AB19) -> 67.727099 | AC20: =SUMPRODUCT(C20:AB20,C$6:AB$6) -> 3329.3798
A22: Concrete road, IRC:58
A23: Build | C23: =PQC_Capex -> 3200 | D23: 0 | E23: 0 | F23: 0 | G23: 0 | H23: 0 | I23: 0 | J23: 0 | K23: 0 | L23: 0 | M23: 0 | N23: 0 | O23: 0 | P23: 0 | Q23: 0 | R23: 0 | S23: 0 | T23: 0 | U23: 0 | V23: 0 | W23: 0 | X23: 0 | Y23: 0 | Z23: 0 | AA23: 0 | AB23: 0 | AC23: =SUMPRODUCT(C23:AB23,C$6:AB$6) -> 3200
A24: Routine maintenance | C24: 0 | D24: =PQC_Routine*D$7 -> 10.5 | E24: =PQC_Routine*E$7 -> 11.025 | F24: =PQC_Routine*F$7 -> 11.57625 | G24: =PQC_Routine*G$7 -> 12.155062 | H24: =PQC_Routine*H$7 -> 12.762816 | I24: =PQC_Routine*I$7 -> 13.400956 | J24: =PQC_Routine*J$7 -> 14.071004 | K24: =PQC_Routine*K$7 -> 14.774554 | ... AB24: =PQC_Routine*AB$7 -> 33.863549 | AC24: =SUMPRODUCT(C24:AB24,C$6:AB$6) -> 144.36513
A25: Joint reseal and slab repairs | C25: 0 | D25: =IF(AND(MOD(D$5,PQC_Cycle)=0,D$5<25),PQC_Repair*D$7,0) -> 0 | E25: =IF(AND(MOD(E$5,PQC_Cycle)=0,E$5<25),PQC_Repair*E$7,0) -> 0 | F25: =IF(AND(MOD(F$5,PQC_Cycle)=0,F$5<25),PQC_Repair*F$7,0) -> 0 | G25: =IF(AND(MOD(G$5,PQC_Cycle)=0,G$5<25),PQC_Repair*G$7,0) -> 0 | H25: =IF(AND(MOD(H$5,PQC_Cycle)=0,H$5<25),PQC_Repair*H$7,0) -> 0 | I25: =IF(AND(MOD(I$5,PQC_Cycle)=0,I$5<25),PQC_Repair*I$7,0) -> 0 | J25: =IF(AND(MOD(J$5,PQC_Cycle)=0,J$5<25),PQC_Repair*J$7,0) -> 0 | K25: =IF(AND(MOD(K$5,PQC_Cycle)=0,K$5<25),PQC_Repair*K$7,0) -> 0 | ... AB25: =IF(AND(MOD(AB$5,PQC_Cycle)=0,AB$5<25),PQC_Repair*AB$7,0) -> 0 | AC25: =SUMPRODUCT(C25:AB25,C$6:AB$6) -> 153.36078
A26: Total | C26: =SUM(C23:C25) -> 3200 | D26: =SUM(D23:D25) -> 10.5 | E26: =SUM(E23:E25) -> 11.025 | F26: =SUM(F23:F25) -> 11.57625 | G26: =SUM(G23:G25) -> 12.155062 | H26: =SUM(H23:H25) -> 12.762816 | I26: =SUM(I23:I25) -> 13.400956 | J26: =SUM(J23:J25) -> 14.071004 | ... AB26: =SUM(AB23:AB25) -> 33.863549 | AC26: =SUMPRODUCT(C26:AB26,C$6:AB$6) -> 3497.7259
A28: GridMats S1: cement-treated gravel
A29: Build | C29: =S1_Capex -> 2029.2 | D29: 0 | E29: 0 | F29: 0 | G29: 0 | H29: 0 | I29: 0 | J29: 0 | K29: 0 | L29: 0 | M29: 0 | N29: 0 | O29: 0 | P29: 0 | Q29: 0 | R29: 0 | S29: 0 | T29: 0 | U29: 0 | V29: 0 | W29: 0 | X29: 0 | Y29: 0 | Z29: 0 | AA29: 0 | AB29: 0 | AC29: =SUMPRODUCT(C29:AB29,C$6:AB$6) -> 2029.2
A30: Routine upkeep | C30: 0 | D30: =GM_RoutinePct*S1_Capex*D$7 -> 10.6533 | E30: =GM_RoutinePct*S1_Capex*E$7 -> 11.185965 | F30: =GM_RoutinePct*S1_Capex*F$7 -> 11.745263 | G30: =GM_RoutinePct*S1_Capex*G$7 -> 12.332526 | H30: =GM_RoutinePct*S1_Capex*H$7 -> 12.949153 | I30: =GM_RoutinePct*S1_Capex*I$7 -> 13.59661 | J30: =GM_RoutinePct*S1_Capex*J$7 -> 14.276441 | K30: =GM_RoutinePct*S1_Capex*K$7 -> 14.990263 | ... AB30: =GM_RoutinePct*S1_Capex*AB$7 -> 34.357957 | AC30: =SUMPRODUCT(C30:AB30,C$6:AB$6) -> 146.47286
A31: Chip-and-cement top-up | C31: 0 | D31: =IF(AND(MOD(D$5,S1_Cycle)=0,D$5<25),S1_TopUp*D$7,0) -> 0 | E31: =IF(AND(MOD(E$5,S1_Cycle)=0,E$5<25),S1_TopUp*E$7,0) -> 0 | F31: =IF(AND(MOD(F$5,S1_Cycle)=0,F$5<25),S1_TopUp*F$7,0) -> 0 | G31: =IF(AND(MOD(G$5,S1_Cycle)=0,G$5<25),S1_TopUp*G$7,0) -> 0 | H31: =IF(AND(MOD(H$5,S1_Cycle)=0,H$5<25),S1_TopUp*H$7,0) -> 0 | I31: =IF(AND(MOD(I$5,S1_Cycle)=0,I$5<25),S1_TopUp*I$7,0) -> 0 | J31: =IF(AND(MOD(J$5,S1_Cycle)=0,J$5<25),S1_TopUp*J$7,0) -> 0 | K31: =IF(AND(MOD(K$5,S1_Cycle)=0,K$5<25),S1_TopUp*K$7,0) -> 0 | ... AB31: =IF(AND(MOD(AB$5,S1_Cycle)=0,AB$5<25),S1_TopUp*AB$7,0) -> 0 | AC31: =SUMPRODUCT(C31:AB31,C$6:AB$6) -> 153.36078
A32: Total | C32: =SUM(C29:C31) -> 2029.2 | D32: =SUM(D29:D31) -> 10.6533 | E32: =SUM(E29:E31) -> 11.185965 | F32: =SUM(F29:F31) -> 11.745263 | G32: =SUM(G29:G31) -> 12.332526 | H32: =SUM(H29:H31) -> 12.949153 | I32: =SUM(I29:I31) -> 13.59661 | J32: =SUM(J29:J31) -> 14.276441 | ... AB32: =SUM(AB29:AB31) -> 34.357957 | AC32: =SUMPRODUCT(C32:AB32,C$6:AB$6) -> 2329.0336
A34: GridMats S2: permeable stone chip
A35: Build | C35: =S2_Capex -> 1681.5 | D35: 0 | E35: 0 | F35: 0 | G35: 0 | H35: 0 | I35: 0 | J35: 0 | K35: 0 | L35: 0 | M35: 0 | N35: 0 | O35: 0 | P35: 0 | Q35: 0 | R35: 0 | S35: 0 | T35: 0 | U35: 0 | V35: 0 | W35: 0 | X35: 0 | Y35: 0 | Z35: 0 | AA35: 0 | AB35: 0 | AC35: =SUMPRODUCT(C35:AB35,C$6:AB$6) -> 1681.5
A36: Routine upkeep | C36: 0 | D36: =GM_RoutinePct*S2_Capex*D$7 -> 8.827875 | E36: =GM_RoutinePct*S2_Capex*E$7 -> 9.2692688 | F36: =GM_RoutinePct*S2_Capex*F$7 -> 9.7327322 | G36: =GM_RoutinePct*S2_Capex*G$7 -> 10.219369 | H36: =GM_RoutinePct*S2_Capex*H$7 -> 10.730337 | I36: =GM_RoutinePct*S2_Capex*I$7 -> 11.266854 | J36: =GM_RoutinePct*S2_Capex*J$7 -> 11.830197 | K36: =GM_RoutinePct*S2_Capex*K$7 -> 12.421707 | ... AB36: =GM_RoutinePct*S2_Capex*AB$7 -> 28.470779 | AC36: =SUMPRODUCT(C36:AB36,C$6:AB$6) -> 121.37498
A37: Chip top-up | C37: 0 | D37: =IF(AND(MOD(D$5,S2_Cycle)=0,D$5<25),S2_TopUp*D$7,0) -> 0 | E37: =IF(AND(MOD(E$5,S2_Cycle)=0,E$5<25),S2_TopUp*E$7,0) -> 0 | F37: =IF(AND(MOD(F$5,S2_Cycle)=0,F$5<25),S2_TopUp*F$7,0) -> 40.516875 | G37: =IF(AND(MOD(G$5,S2_Cycle)=0,G$5<25),S2_TopUp*G$7,0) -> 0 | H37: =IF(AND(MOD(H$5,S2_Cycle)=0,H$5<25),S2_TopUp*H$7,0) -> 0 | I37: =IF(AND(MOD(I$5,S2_Cycle)=0,I$5<25),S2_TopUp*I$7,0) -> 46.903347 | J37: =IF(AND(MOD(J$5,S2_Cycle)=0,J$5<25),S2_TopUp*J$7,0) -> 0 | K37: =IF(AND(MOD(K$5,S2_Cycle)=0,K$5<25),S2_TopUp*K$7,0) -> 0 | ... AB37: =IF(AND(MOD(AB$5,S2_Cycle)=0,AB$5<25),S2_TopUp*AB$7,0) -> 0 | AC37: =SUMPRODUCT(C37:AB37,C$6:AB$6) -> 157.17622
A38: Dust suppression (residual) | C38: 0 | D38: =IF(D$5<=DustYears,DustCost*(1-DustCutS2)*D$7,0) -> 23.625 | E38: =IF(E$5<=DustYears,DustCost*(1-DustCutS2)*E$7,0) -> 24.80625 | F38: =IF(F$5<=DustYears,DustCost*(1-DustCutS2)*F$7,0) -> 0 | G38: =IF(G$5<=DustYears,DustCost*(1-DustCutS2)*G$7,0) -> 0 | H38: =IF(H$5<=DustYears,DustCost*(1-DustCutS2)*H$7,0) -> 0 | I38: =IF(I$5<=DustYears,DustCost*(1-DustCutS2)*I$7,0) -> 0 | J38: =IF(J$5<=DustYears,DustCost*(1-DustCutS2)*J$7,0) -> 0 | K38: =IF(K$5<=DustYears,DustCost*(1-DustCutS2)*K$7,0) -> 0 | ... AB38: =IF(AB$5<=DustYears,DustCost*(1-DustCutS2)*AB$7,0) -> 0 | AC38: =SUMPRODUCT(C38:AB38,C$6:AB$6) -> 41.978306
A39: Total | C39: =SUM(C35:C38) -> 1681.5 | D39: =SUM(D35:D38) -> 32.452875 | E39: =SUM(E35:E38) -> 34.075519 | F39: =SUM(F35:F38) -> 50.249607 | G39: =SUM(G35:G38) -> 10.219369 | H39: =SUM(H35:H38) -> 10.730337 | I39: =SUM(I35:I38) -> 58.170202 | J39: =SUM(J35:J38) -> 11.830197 | ... AB39: =SUM(AB35:AB38) -> 28.470779 | AC39: =SUMPRODUCT(C39:AB39,C$6:AB$6) -> 2002.0295
A41: Summary: 25-year life-cycle cost (present value, ₹ / m²)
A42: Surface | C42: Build | D42: PV of upkeep | E42: 25-yr LCC (PV) | F42: ₹ / sq ft | G42: vs build
A43: WBM / gravel | C43: =C14 -> 600 | D43: =AC14-C43 -> 1539.5255 | E43: =AC14 -> 2139.5255 | F43: =E43/10.7639 -> 198.76862 | G43: =E43/C43 -> 3.5658759
A44: Bituminous, IRC:37 | C44: =C20 -> 2000 | D44: =AC20-C44 -> 1329.3798 | E44: =AC20 -> 3329.3798 | F44: =E44/10.7639 -> 309.3098 | G44: =E44/C44 -> 1.6646899
A45: Concrete, IRC:58 | C45: =C26 -> 3200 | D45: =AC26-C45 -> 297.72591 | E45: =AC26 -> 3497.7259 | F45: =E45/10.7639 -> 324.94968 | G45: =E45/C45 -> 1.0930393
A46: GridMats S1 | C46: =C32 -> 2029.2 | D46: =AC32-C46 -> 299.83364 | E46: =AC32 -> 2329.0336 | F46: =E46/10.7639 -> 216.37451 | G46: =E46/C46 -> 1.1477595
A47: GridMats S2 | C47: =C39 -> 1681.5 | D47: =AC39-C47 -> 320.5295 | E47: =AC39 -> 2002.0295 | F47: =E47/10.7639 -> 185.99481 | G47: =E47/C47 -> 1.1906212
A49: Like-for-like comparisons (₹ / m²)
A50: Comparison | C50: Extra build cost | D50: Upkeep saved (PV) | E50: Net 25-yr saving | F50: Saving %
A51: O&M tracks: GridMats S2 vs WBM | C51: =C47-C43 -> 1081.5 | D51: =D43-D47 -> 1218.996 | E51: =E43-E47 -> 137.49601 | F51: =E51/E43 -> 0.064264722
A52: Main roads: GridMats S1 vs bituminous | C52: =C46-C44 -> 29.2 | D52: =D44-D46 -> 1029.5461 | E52: =E44-E46 -> 1000.3461 | F52: =E52/E44 -> 0.30046021
A53: Main roads: GridMats S1 vs concrete | C53: =C46-C45 -> -1170.8 | D53: =D45-D46 -> -2.1077309 | E53: =E45-E46 -> 1168.6923 | F53: =E53/E45 -> 0.33412917

Sheet Solar Park 100MW
A1: Solar park block: GridMats roads vs conventional roads
A2: Per solar block (default 100 MWp). ₹ lakh unless stated. Positive = benefit to Reliance. Scenario set on Inputs.
A4: Quantities
A5: Block size (MWp) | B5: =BlockMWp -> 100
A6: Road length (km) | B6: =BlockMWp/100*RoadKm -> 10
A7: Main roads, GridMats S1 (m²) | B7: =BlockMWp/100*RoadKm*MainShare*1000*MainWidth -> 18000
A8: O&M tracks, GridMats S2 (m²) | B8: =BlockMWp/100*RoadKm*(1-MainShare)*1000*TrackWidth -> 31500
A9: Total GridMats area (m²) | B9: =MainArea+TrackArea -> 49500
A10: Main roads would otherwise be | B10: =MainBaseline -> Bituminous
A13: Year | C13: 0 | D13: 1 | E13: 2 | F13: 3 | G13: 4 | H13: 5 | I13: 6 | J13: 7 | K13: 8 | L13: 9 | M13: 10 | N13: 11 | O13: 12 | P13: 13 | Q13: 14 | R13: 15 | S13: 16 | T13: 17 | U13: 18 | V13: 19 | W13: 20 | X13: 21 | Y13: 22 | Z13: 23 | AA13: 24 | AB13: 25 | AC13: PV / total
A14: Discount factor | C14: =1/(1+DiscRate)^C$13 -> 1 | D14: =1/(1+DiscRate)^D$13 -> 0.90909091 | E14: =1/(1+DiscRate)^E$13 -> 0.82644628 | F14: =1/(1+DiscRate)^F$13 -> 0.7513148 | G14: =1/(1+DiscRate)^G$13 -> 0.68301346 | H14: =1/(1+DiscRate)^H$13 -> 0.62092132 | I14: =1/(1+DiscRate)^I$13 -> 0.56447393 | J14: =1/(1+DiscRate)^J$13 -> 0.51315812 | ... AB14: =1/(1+DiscRate)^AB$13 -> 0.092295998
A15: Cost index | C15: =(1+CostEsc)^C$13 -> 1 | D15: =(1+CostEsc)^D$13 -> 1.05 | E15: =(1+CostEsc)^E$13 -> 1.1025 | F15: =(1+CostEsc)^F$13 -> 1.157625 | G15: =(1+CostEsc)^G$13 -> 1.2155063 | H15: =(1+CostEsc)^H$13 -> 1.2762816 | I15: =(1+CostEsc)^I$13 -> 1.3400956 | J15: =(1+CostEsc)^J$13 -> 1.4071004 | ... AB15: =(1+CostEsc)^AB$13 -> 3.3863549
A16: Energy index (degradation × value escalation) | C16: 0 | D16: =(1-Degr)^(D$13-1)*(1+EnergyEsc)^(D$13-1) -> 1 | E16: =(1-Degr)^(E$13-1)*(1+EnergyEsc)^(E$13-1) -> 0.996 | F16: =(1-Degr)^(F$13-1)*(1+EnergyEsc)^(F$13-1) -> 0.992016 | G16: =(1-Degr)^(G$13-1)*(1+EnergyEsc)^(G$13-1) -> 0.98804794 | H16: =(1-Degr)^(H$13-1)*(1+EnergyEsc)^(H$13-1) -> 0.98409574 | I16: =(1-Degr)^(I$13-1)*(1+EnergyEsc)^(I$13-1) -> 0.98015936 | J16: =(1-Degr)^(J$13-1)*(1+EnergyEsc)^(J$13-1) -> 0.97623872 | K16: =(1-Degr)^(K$13-1)*(1+EnergyEsc)^(K$13-1) -> 0.97233377 | ... AB16: =(1-Degr)^(AB$13-1)*(1+EnergyEsc)^(AB$13-1) -> 0.90828914
A17: Carbon value index | C17: =(1+CarbonEsc)^C$13 -> 1 | D17: =(1+CarbonEsc)^D$13 -> 1.05 | E17: =(1+CarbonEsc)^E$13 -> 1.1025 | F17: =(1+CarbonEsc)^F$13 -> 1.157625 | G17: =(1+CarbonEsc)^G$13 -> 1.2155063 | H17: =(1+CarbonEsc)^H$13 -> 1.2762816 | I17: =(1+CarbonEsc)^I$13 -> 1.3400956 | J17: =(1+CarbonEsc)^J$13 -> 1.4071004 | ... AB17: =(1+CarbonEsc)^AB$13 -> 3.3863549
A18: Road costs (₹ lakh)
A19: Conventional main roads | C19: =MainArea*IF(MainBaseline="PQC",'Road LCC'!C26,'Road LCC'!C20)/100000 -> 360 | D19: =MainArea*IF(MainBaseline="PQC",'Road LCC'!D26,'Road LCC'!D20)/100000 -> 3.78 | E19: =MainArea*IF(MainBaseline="PQC",'Road LCC'!E26,'Road LCC'!E20)/100000 -> 3.969 | F19: =MainArea*IF(MainBaseline="PQC",'Road LCC'!F26,'Road LCC'!F20)/100000 -> 4.16745 | G19: =MainArea*IF(MainBaseline="PQC",'Road LCC'!G26,'Road LCC'!G20)/100000 -> 4.3758225 | H19: =MainArea*IF(MainBaseline="PQC",'Road LCC'!H26,'Road LCC'!H20)/100000 -> 107.97342 | I19: =MainArea*IF(MainBaseline="PQC",'Road LCC'!I26,'Road LCC'!I20)/100000 -> 4.8243443 | J19: =MainArea*IF(MainBaseline="PQC",'Road LCC'!J26,'Road LCC'!J20)/100000 -> 5.0655615 | ... AB19: =MainArea*IF(MainBaseline="PQC",'Road LCC'!AB26,'Road LCC'!AB20)/100000 -> 12.190878 | AC19: =SUMPRODUCT(C19:AB19,C$14:AB$14) -> 599.28836
A20: Conventional O&M tracks (WBM) | C20: =TrackArea*'Road LCC'!C14/100000 -> 189 | D20: =TrackArea*'Road LCC'!D14/100000 -> 38.03625 | E20: =TrackArea*'Road LCC'!E14/100000 -> 39.938063 | F20: =TrackArea*'Road LCC'!F14/100000 -> 14.586075 | G20: =TrackArea*'Road LCC'!G14/100000 -> 111.0365 | H20: =TrackArea*'Road LCC'!H14/100000 -> 16.081148 | I20: =TrackArea*'Road LCC'!I14/100000 -> 16.885205 | J20: =TrackArea*'Road LCC'!J14/100000 -> 17.729465 | ... AB20: =TrackArea*'Road LCC'!AB14/100000 -> 42.668072 | AC20: =SUMPRODUCT(C20:AB20,C$14:AB$14) -> 673.95054
A21: GridMats S1 main roads | C21: =MainArea*'Road LCC'!C32/100000 -> 365.256 | D21: =MainArea*'Road LCC'!D32/100000 -> 1.917594 | E21: =MainArea*'Road LCC'!E32/100000 -> 2.0134737 | F21: =MainArea*'Road LCC'!F32/100000 -> 2.1141474 | G21: =MainArea*'Road LCC'!G32/100000 -> 2.2198548 | H21: =MainArea*'Road LCC'!H32/100000 -> 2.3308475 | I21: =MainArea*'Road LCC'!I32/100000 -> 2.4473899 | J21: =MainArea*'Road LCC'!J32/100000 -> 2.5697594 | ... AB21: =MainArea*'Road LCC'!AB32/100000 -> 6.1844323 | AC21: =SUMPRODUCT(C21:AB21,C$14:AB$14) -> 419.22605
A22: GridMats S2 O&M tracks | C22: =TrackArea*'Road LCC'!C39/100000 -> 529.6725 | D22: =TrackArea*'Road LCC'!D39/100000 -> 10.222656 | E22: =TrackArea*'Road LCC'!E39/100000 -> 10.733788 | F22: =TrackArea*'Road LCC'!F39/100000 -> 15.828626 | G22: =TrackArea*'Road LCC'!G39/100000 -> 3.2191012 | H22: =TrackArea*'Road LCC'!H39/100000 -> 3.3800562 | I22: =TrackArea*'Road LCC'!I39/100000 -> 18.323613 | J22: =TrackArea*'Road LCC'!J39/100000 -> 3.726512 | ... AB22: =TrackArea*'Road LCC'!AB39/100000 -> 8.9682954 | AC22: =SUMPRODUCT(C22:AB22,C$14:AB$14) -> 630.63929
A23: Road cost saving (conventional − GridMats) | C23: =C19+C20-C21-C22 -> -345.9285 | D23: =D19+D20-D21-D22 -> 29.676 | E23: =E19+E20-E21-E22 -> 31.1598 | F23: =F19+F20-F21-F22 -> 0.81075135 | G23: =G19+G20-G21-G22 -> 109.97336 | H23: =H19+H20-H21-H22 -> 118.34366 | I23: =I19+I20-I21-I22 -> 0.93854603 | J23: =J19+J20-J21-J22 -> 16.498755 | ... AB23: =AB19+AB20-AB21-AB22 -> 39.706222 | AC23: =SUMPRODUCT(C23:AB23,C$14:AB$14) -> 223.37355
A24: Energy, cleaning and carbon
A25: Extra energy from cleaner modules (MWh) | C25: 0 | D25: =BlockMWp*Yield*SoilingLoss*DustShare*DustCutS2*D16 -> 589.05 | E25: =BlockMWp*Yield*SoilingLoss*DustShare*DustCutS2*E16 -> 586.6938 | F25: =BlockMWp*Yield*SoilingLoss*DustShare*DustCutS2*F16 -> 584.34702 | G25: =BlockMWp*Yield*SoilingLoss*DustShare*DustCutS2*G16 -> 582.00964 | H25: =BlockMWp*Yield*SoilingLoss*DustShare*DustCutS2*H16 -> 579.6816 | I25: =BlockMWp*Yield*SoilingLoss*DustShare*DustCutS2*I16 -> 577.36287 | J25: =BlockMWp*Yield*SoilingLoss*DustShare*DustCutS2*J16 -> 575.05342 | K25: =BlockMWp*Yield*SoilingLoss*DustShare*DustCutS2*K16 -> 572.75321 | ... AB25: =BlockMWp*Yield*SoilingLoss*DustShare*DustCutS2*AB16 -> 535.02772 | AC25: =SUM(C25:AB25) -> 14040.598
A26: Value of extra energy (₹ lakh) | C26: 0 | D26: =D25*1000*EnergyValue/100000 -> 15.90435 | E26: =E25*1000*EnergyValue/100000 -> 15.840733 | F26: =F25*1000*EnergyValue/100000 -> 15.77737 | G26: =G25*1000*EnergyValue/100000 -> 15.71426 | H26: =H25*1000*EnergyValue/100000 -> 15.651403 | I26: =I25*1000*EnergyValue/100000 -> 15.588798 | J26: =J25*1000*EnergyValue/100000 -> 15.526442 | K26: =K25*1000*EnergyValue/100000 -> 15.464337 | ... AB26: =AB25*1000*EnergyValue/100000 -> 14.445748 | AC26: =SUMPRODUCT(C26:AB26,C$14:AB$14) -> 140.15768
A27: Module-cleaning cost avoided (₹ lakh) | C27: 0 | D27: =BlockMWp*CleanCost*CleanSave*D15 -> 0 | E27: =BlockMWp*CleanCost*CleanSave*E15 -> 0 | F27: =BlockMWp*CleanCost*CleanSave*F15 -> 0 | G27: =BlockMWp*CleanCost*CleanSave*G15 -> 0 | H27: =BlockMWp*CleanCost*CleanSave*H15 -> 0 | I27: =BlockMWp*CleanCost*CleanSave*I15 -> 0 | J27: =BlockMWp*CleanCost*CleanSave*J15 -> 0 | K27: =BlockMWp*CleanCost*CleanSave*K15 -> 0 | ... AB27: =BlockMWp*CleanCost*CleanSave*AB15 -> 0 | AC27: =SUMPRODUCT(C27:AB27,C$14:AB$14) -> 0
A28: Earlier energisation (₹ lakh) | C28: 0 | D28: =IF(D$13=1,DaysEarly*BlockMWp*Yield/365*1000*EnergyValue/100000,0) -> 0 | E28: =IF(E$13=1,DaysEarly*BlockMWp*Yield/365*1000*EnergyValue/100000,0) -> 0 | F28: =IF(F$13=1,DaysEarly*BlockMWp*Yield/365*1000*EnergyValue/100000,0) -> 0 | G28: =IF(G$13=1,DaysEarly*BlockMWp*Yield/365*1000*EnergyValue/100000,0) -> 0 | H28: =IF(H$13=1,DaysEarly*BlockMWp*Yield/365*1000*EnergyValue/100000,0) -> 0 | I28: =IF(I$13=1,DaysEarly*BlockMWp*Yield/365*1000*EnergyValue/100000,0) -> 0 | J28: =IF(J$13=1,DaysEarly*BlockMWp*Yield/365*1000*EnergyValue/100000,0) -> 0 | K28: =IF(K$13=1,DaysEarly*BlockMWp*Yield/365*1000*EnergyValue/100000,0) -> 0 | ... AB28: =IF(AB$13=1,DaysEarly*BlockMWp*Yield/365*1000*EnergyValue/100000,0) -> 0 | AC28: =SUMPRODUCT(C28:AB28,C$14:AB$14) -> 0
A29: CO2e avoided: plastic reuse and paving materials (t) | C29: =(ParkArea*PlasticHD*PPCredit+MainArea*IF(MainBaseline="PQC",(PQC_Cement-S1_Cement)*CementEF,BT_Binder*BitumenEF+BT_Mix*HotMixEF-S1_Cement*CementEF))/1000 -> 548.865 | D29: =IF(AND(MainBaseline<>"PQC",'Road LCC'!D19>0),MainArea*(OV_Binder*BitumenEF+OV_Mix*HotMixEF)/1000,0) -> 0 | E29: =IF(AND(MainBaseline<>"PQC",'Road LCC'!E19>0),MainArea*(OV_Binder*BitumenEF+OV_Mix*HotMixEF)/1000,0) -> 0 | F29: =IF(AND(MainBaseline<>"PQC",'Road LCC'!F19>0),MainArea*(OV_Binder*BitumenEF+OV_Mix*HotMixEF)/1000,0) -> 0 | G29: =IF(AND(MainBaseline<>"PQC",'Road LCC'!G19>0),MainArea*(OV_Binder*BitumenEF+OV_Mix*HotMixEF)/1000,0) -> 0 | H29: =IF(AND(MainBaseline<>"PQC",'Road LCC'!H19>0),MainArea*(OV_Binder*BitumenEF+OV_Mix*HotMixEF)/1000,0) -> 88.83 | I29: =IF(AND(MainBaseline<>"PQC",'Road LCC'!I19>0),MainArea*(OV_Binder*BitumenEF+OV_Mix*HotMixEF)/1000,0) -> 0 | J29: =IF(AND(MainBaseline<>"PQC",'Road LCC'!J19>0),MainArea*(OV_Binder*BitumenEF+OV_Mix*HotMixEF)/1000,0) -> 0 | K29: =IF(AND(MainBaseline<>"PQC",'Road LCC'!K19>0),MainArea*(OV_Binder*BitumenEF+OV_Mix*HotMixEF)/1000,0) -> 0 | ... AB29: =IF(AND(MainBaseline<>"PQC",'Road LCC'!AB19>0),MainArea*(OV_Binder*BitumenEF+OV_Mix*HotMixEF)/1000,0) -> 0 | AC29: =SUM(C29:AB29) -> 904.185
A30: CO2e avoided: extra renewable energy (t) | C30: 0 | D30: =D25*GridEF -> 418.2255 | E30: =E25*GridEF -> 416.5526 | F30: =F25*GridEF -> 414.88639 | G30: =G25*GridEF -> 413.22684 | H30: =H25*GridEF -> 411.57393 | I30: =I25*GridEF -> 409.92764 | J30: =J25*GridEF -> 408.28793 | K30: =K25*GridEF -> 406.65478 | ... AB30: =AB25*GridEF -> 379.86968 | AC30: =SUM(C30:AB30) -> 9968.8246
A31: Carbon value: materials (₹ lakh) | C31: =C29*CarbonPrice*C17/100000 -> 3.842055 | D31: =D29*CarbonPrice*D17/100000 -> 0 | E31: =E29*CarbonPrice*E17/100000 -> 0 | F31: =F29*CarbonPrice*F17/100000 -> 0 | G31: =G29*CarbonPrice*G17/100000 -> 0 | H31: =H29*CarbonPrice*H17/100000 -> 0.79360464 | I31: =I29*CarbonPrice*I17/100000 -> 0 | J31: =J29*CarbonPrice*J17/100000 -> 0 | ... AB31: =AB29*CarbonPrice*AB17/100000 -> 0 | AC31: =SUMPRODUCT(C31:AB31,C$14:AB$14) -> 5.2800245
A32: Carbon value: extra energy (₹ lakh) | C32: 0 | D32: =D30*CarbonPrice*D17/100000 -> 3.0739574 | E32: =E30*CarbonPrice*E17/100000 -> 3.2147447 | F32: =F30*CarbonPrice*F17/100000 -> 3.36198 | G32: =G30*CarbonPrice*G17/100000 -> 3.5159587 | H32: =H30*CarbonPrice*H17/100000 -> 3.6769896 | I32: =I30*CarbonPrice*I17/100000 -> 3.8453957 | J32: =J30*CarbonPrice*J17/100000 -> 4.0215148 | K32: =K30*CarbonPrice*K17/100000 -> 4.2057002 | ... AB32: =AB30*CarbonPrice*AB17/100000 -> 9.004615 | AC32: =SUMPRODUCT(C32:AB32,C$14:AB$14) -> 40.679033
A34: NET BENEFIT TO RELIANCE (₹ lakh) | C34: =C23+C26+C27+C28+C31+C32 -> -342.08645 | D34: =D23+D26+D27+D28+D31+D32 -> 48.654308 | E34: =E23+E26+E27+E28+E31+E32 -> 50.215278 | F34: =F23+F26+F27+F28+F31+F32 -> 19.950101 | G34: =G23+G26+G27+G28+G31+G32 -> 129.20358 | H34: =H23+H26+H27+H28+H31+H32 -> 138.46566 | I34: =I23+I26+I27+I28+I31+I32 -> 20.372739 | J34: =J23+J26+J27+J28+J31+J32 -> 36.046713 | ... AB34: =AB23+AB26+AB27+AB28+AB31+AB32 -> 63.156586 | AC34: =SUMPRODUCT(C34:AB34,C$14:AB$14) -> 409.49028
A35: Cumulative (₹ lakh) | C35: =C34 -> -342.08645 | D35: =C35+D34 -> -293.43214 | E35: =D35+E34 -> -243.21686 | F35: =E35+F34 -> -223.26676 | G35: =F35+G34 -> -94.063177 | H35: =G35+H34 -> 44.402484 | I35: =H35+I34 -> 64.775224 | J35: =I35+J34 -> 100.82194 | K35: =J35+K34 -> 254.16528 | ... AB35: =AA35+AB34 -> 2114.6136
A37: Results per block
A38: NPV over 25 years (₹ Cr) | B38: =AC34/100 -> 4.0949028
A39: NPV per MW (₹ lakh) | B39: =AC34/BlockMWp -> 4.0949028
A40: Up-front GridMats premium (₹ Cr) | B40: =-C23/100 -> 3.459285
A41: Premium as % of solar plant capex | B41: =Park_Premium/(BlockMWp*SolarCapex) -> 0.0086482125
A42: IRR on the premium | B42: =IFERROR(IRR(C34:AB34),"no premium") -> 0.20861507
A43: Simple payback (years) | B43: =IF(C35>=0,0,IF(COUNTIF(D35:AB35,"<0")>=25,"> 25",COUNTIF(D35:AB35,"<0")+(-INDEX(C35:AB35,COUNTIF(D35:AB35,"<0")+1))/INDEX(C34:AB34,COUNTIF(D35:AB35,"<0")+2))) -> 4.6793249
A44: PV of road upkeep saved, years 1-25 (₹ Cr) | B44: =(AC23-C23)/100 -> 5.6930205
A45: PV of extra energy (₹ Cr) | B45: =AC26/100 -> 1.4015768
A46: PV of cleaning saved (₹ Cr) | B46: =AC27/100 -> 0
A47: PV of earlier energisation (₹ Cr) | B47: =AC28/100 -> 0
A48: PV of carbon value (₹ Cr) | B48: =(AC31+AC32)/100 -> 0.45959057
A49: Benefit-to-premium ratio | B49: =IFERROR((PV_Upkeep+PV_Energy+PV_Clean+PV_Early+PV_Carbon)/Park_Premium,"n/a") -> 2.1837425
A50: NPV at 8% discount rate (₹ Cr) | B50: =(NPV(0.08,D34:AB34)+C34)/100 -> 5.7078719
A51: NPV at 12% discount rate (₹ Cr) | B51: =(NPV(0.12,D34:AB34)+C34)/100 -> 2.8789415
A52: Extra clean energy over 25 years (MWh) | B52: =AC25 -> 14040.598
A53: CO2e avoided over 25 years (t) | B53: =AC29+AC30 -> 10873.01
A54: Recycled PP used (t) | B54: =ParkArea*PlasticHD/1000 -> 326.7
A55: Road upkeep saved, years 1-25, undiscounted (₹ Cr) | B55: =(SUM(D23:AB23))/100 -> 19.343599
A57: Scenario building blocks (used by the Sensitivity sheet)
A58: PV of road costs incl. build, per block (₹ Cr) | B58: =AC23/100 -> 2.2337355
A59: PV of energy per unit dust share per ₹/kWh (₹ Cr) | B59: =BlockMWp*Yield*SoilingLoss*DustCutS2*1000*SUMPRODUCT(D16:AB16,D14:AB14)/10000000 -> 3.4606834
A60: PV of cleaning per 100% saving (₹ Cr) | B60: =BlockMWp*CleanCost*SUMPRODUCT(D15:AB15,D14:AB14)/100 -> 21.654769
A61: PV of earlier energisation per day per ₹/kWh (₹ Cr) | B61: =BlockMWp*Yield/365*1000*D14/10000000 -> 0.046575342
A62: PV of materials carbon per ₹/t (₹ Cr) | B62: =SUMPRODUCT(C29:AB29,C17:AB17,C14:AB14)/10000000 -> 7.5428922e-05
A63: PV of energy carbon per unit dust share per ₹/t (₹ Cr) | B63: =BlockMWp*Yield*SoilingLoss*DustCutS2*GridEF*SUMPRODUCT(D16:AB16,D17:AB17,D14:AB14)/10000000 -> 0.0038741936
A64: PV factor of escalating costs, years 1-25 | B64: =SUMPRODUCT(D15:AB15,D14:AB14) -> 14.436513
A65: Check: rebuilt NPV − model NPV (should be 0) | B65: =U_Road+U_Energy*DustShare*EnergyValue+U_Clean*CleanSave+U_Early*DaysEarly*EnergyValue+U_CarbMat*CarbonPrice+U_CarbEn*DustShare*CarbonPrice-Park_NPV -> 0

Sheet Solar Walkway
A1: GridMats Solar Walkway: economics per m² of walkway
A2: Pre-commercial product. Rated power and price are from GridMats; yield and life are assumptions that the pilot will measure.
A4: Inputs in use
A5: Site | B5: =Site -> Navi Mumbai
A6: Rated power (kWp per m²) | B6: =PowerDens/1000 -> 0.16
A7: Yield (kWh / kWp / yr) | B7: =IF(Site="Navi Mumbai",WkYieldMum,WkYieldJam)*WkYieldMult -> 1150
A8: Grid power cost avoided (₹ / kWh, year 1) | B8: =IF(Site="Navi Mumbai",TariffMum,TariffJam) -> 12
A9: Solar walkway installed (₹ / m²) | B9: =WkTotal -> 12578
A10: Less: paver walkway it replaces (₹ / m²) | B10: =-Paver_Capex -> -1100
A11: Extra investment for a generating walkway (₹ / m²) | B11: =WkTotal-Paver_Capex -> 11478
A12: Depreciable solar part (₹ / m²) | B12: =SolarLayer+BOS*WkKWp -> 11500
A15: Year | C15: 0 | D15: 1 | E15: 2 | F15: 3 | G15: 4 | H15: 5 | I15: 6 | J15: 7 | K15: 8 | L15: 9 | M15: 10 | N15: 11 | O15: 12 | P15: 13 | Q15: 14 | R15: 15 | S15: 16 | T15: 17 | U15: 18 | V15: 19 | W15: 20 | X15: 21 | Y15: 22 | Z15: 23 | AA15: 24 | AB15: 25 | AC15: PV / total
A16: Discount factor | C16: =1/(1+DiscRate)^C$15 -> 1 | D16: =1/(1+DiscRate)^D$15 -> 0.90909091 | E16: =1/(1+DiscRate)^E$15 -> 0.82644628 | F16: =1/(1+DiscRate)^F$15 -> 0.7513148 | G16: =1/(1+DiscRate)^G$15 -> 0.68301346 | H16: =1/(1+DiscRate)^H$15 -> 0.62092132 | I16: =1/(1+DiscRate)^I$15 -> 0.56447393 | J16: =1/(1+DiscRate)^J$15 -> 0.51315812 | ... AB16: =1/(1+DiscRate)^AB$15 -> 0.092295998
A17: Cost index | C17: =(1+CostEsc)^C$15 -> 1 | D17: =(1+CostEsc)^D$15 -> 1.05 | E17: =(1+CostEsc)^E$15 -> 1.1025 | F17: =(1+CostEsc)^F$15 -> 1.157625 | G17: =(1+CostEsc)^G$15 -> 1.2155063 | H17: =(1+CostEsc)^H$15 -> 1.2762816 | I17: =(1+CostEsc)^I$15 -> 1.3400956 | J17: =(1+CostEsc)^J$15 -> 1.4071004 | ... AB17: =(1+CostEsc)^AB$15 -> 3.3863549
A18: Generation (kWh per m²) | C18: 0 | D18: =IF(D$15<=WkLife,WkKWp*WkYield*(1-WkDegr)^(D$15-1),0) -> 184 | E18: =IF(E$15<=WkLife,WkKWp*WkYield*(1-WkDegr)^(E$15-1),0) -> 182.712 | F18: =IF(F$15<=WkLife,WkKWp*WkYield*(1-WkDegr)^(F$15-1),0) -> 181.43302 | G18: =IF(G$15<=WkLife,WkKWp*WkYield*(1-WkDegr)^(G$15-1),0) -> 180.16298 | H18: =IF(H$15<=WkLife,WkKWp*WkYield*(1-WkDegr)^(H$15-1),0) -> 178.90184 | I18: =IF(I$15<=WkLife,WkKWp*WkYield*(1-WkDegr)^(I$15-1),0) -> 177.64953 | J18: =IF(J$15<=WkLife,WkKWp*WkYield*(1-WkDegr)^(J$15-1),0) -> 176.40598 | K18: =IF(K$15<=WkLife,WkKWp*WkYield*(1-WkDegr)^(K$15-1),0) -> 175.17114 | ... AB18: =IF(AB$15<=WkLife,WkKWp*WkYield*(1-WkDegr)^(AB$15-1),0) -> 0 | AC18: =SUMPRODUCT(C18:AB18,C$16:AB$16) -> 1497.5176
A19: Power cost avoided (₹ / kWh) | C19: 0 | D19: =WkTariff*(1+TariffEsc)^(D$15-1) -> 12 | E19: =WkTariff*(1+TariffEsc)^(E$15-1) -> 12.36 | F19: =WkTariff*(1+TariffEsc)^(F$15-1) -> 12.7308 | G19: =WkTariff*(1+TariffEsc)^(G$15-1) -> 13.112724 | H19: =WkTariff*(1+TariffEsc)^(H$15-1) -> 13.506106 | I19: =WkTariff*(1+TariffEsc)^(I$15-1) -> 13.911289 | J19: =WkTariff*(1+TariffEsc)^(J$15-1) -> 14.328628 | K19: =WkTariff*(1+TariffEsc)^(K$15-1) -> 14.758486 | ... AB19: =WkTariff*(1+TariffEsc)^(AB$15-1) -> 24.393529
A20: Electricity bill saved (₹) | C20: 0 | D20: =D18*D19 -> 2208 | E20: =E18*E19 -> 2258.3203 | F20: =F18*F19 -> 2309.7874 | G20: =G18*G19 -> 2362.4275 | H20: =H18*H19 -> 2416.2672 | I20: =I18*I19 -> 2471.3339 | J20: =J18*J19 -> 2527.6556 | K20: =K18*K19 -> 2585.2609 | ... AB20: =AB18*AB19 -> 0 | AC20: =SUMPRODUCT(C20:AB20,C$16:AB$16) -> 21926.173
A21: Cleaning and inspection (₹) | C21: 0 | D21: =IF(D$15<=WkLife,-WkOM*D17,0) -> -157.5 | E21: =IF(E$15<=WkLife,-WkOM*E17,0) -> -165.375 | F21: =IF(F$15<=WkLife,-WkOM*F17,0) -> -173.64375 | G21: =IF(G$15<=WkLife,-WkOM*G17,0) -> -182.32594 | H21: =IF(H$15<=WkLife,-WkOM*H17,0) -> -191.44223 | I21: =IF(I$15<=WkLife,-WkOM*I17,0) -> -201.01435 | J21: =IF(J$15<=WkLife,-WkOM*J17,0) -> -211.06506 | K21: =IF(K$15<=WkLife,-WkOM*K17,0) -> -221.61832 | ... AB21: =IF(AB$15<=WkLife,-WkOM*AB17,0) -> 0 | AC21: =SUMPRODUCT(C21:AB21,C$16:AB$16) -> -1907.6532
A22: Inverter replacement (₹) | C22: 0 | D22: =IF(D$15=InvYear,-InvRepl*WkKWp*D17,0) -> 0 | E22: =IF(E$15=InvYear,-InvRepl*WkKWp*E17,0) -> 0 | F22: =IF(F$15=InvYear,-InvRepl*WkKWp*F17,0) -> 0 | G22: =IF(G$15=InvYear,-InvRepl*WkKWp*G17,0) -> 0 | H22: =IF(H$15=InvYear,-InvRepl*WkKWp*H17,0) -> 0 | I22: =IF(I$15=InvYear,-InvRepl*WkKWp*I17,0) -> 0 | J22: =IF(J$15=InvYear,-InvRepl*WkKWp*J17,0) -> 0 | K22: =IF(K$15=InvYear,-InvRepl*WkKWp*K17,0) -> 0 | ... AB22: =IF(AB$15=InvYear,-InvRepl*WkKWp*AB17,0) -> 0 | AC22: =SUMPRODUCT(C22:AB22,C$16:AB$16) -> -366.21771
A23: Extra investment (₹) | C23: =-WkInc -> -11478 | D23: 0 | E23: 0 | F23: 0 | G23: 0 | H23: 0 | I23: 0 | J23: 0 | K23: 0 | L23: 0 | M23: 0 | N23: 0 | O23: 0 | P23: 0 | Q23: 0 | R23: 0 | S23: 0 | T23: 0 | U23: 0 | V23: 0 | W23: 0 | X23: 0 | Y23: 0 | Z23: 0 | AA23: 0 | AB23: 0 | AC23: =SUMPRODUCT(C23:AB23,C$16:AB$16) -> -11478
A24: Net cash flow, pre-tax (₹) | C24: =C20+C21+C22+C23 -> -11478 | D24: =D20+D21+D22+D23 -> 2050.5 | E24: =E20+E21+E22+E23 -> 2092.9453 | F24: =F20+F21+F22+F23 -> 2136.1437 | G24: =G20+G21+G22+G23 -> 2180.1016 | H24: =H20+H21+H22+H23 -> 2224.825 | I24: =I20+I21+I22+I23 -> 2270.3196 | J24: =J20+J21+J22+J23 -> 2316.5906 | ... AB24: =AB20+AB21+AB22+AB23 -> 0 | AC24: =SUMPRODUCT(C24:AB24,C$16:AB$16) -> 8174.3022
A25: Cumulative (₹) | C25: =C24 -> -11478 | D25: =C25+D24 -> -9427.5 | E25: =D25+E24 -> -7334.5547 | F25: =E25+F24 -> -5198.411 | G25: =F25+G24 -> -3018.3094 | H25: =G25+H24 -> -793.48445 | I25: =H25+I24 -> 1476.8352 | J25: =I25+J24 -> 3793.4257 | K25: =J25+K24 -> 6157.0683 | ... AB25: =AA25+AB24 -> 37329.39
A26: Tax written-down value, opening (₹) | C26: =WkSolarPart -> 11500 | D26: =WkSolarPart -> 11500 | E26: =D26-D27 -> 6900 | F26: =E26-E27 -> 4140 | G26: =F26-F27 -> 2484 | H26: =G26-G27 -> 1490.4 | I26: =H26-H27 -> 894.24 | J26: =I26-I27 -> 536.544 | K26: =J26-J27 -> 321.9264 | L26: =K26-K27 -> 193.15584 | ... AB26: =AA26-AA27 -> 0.054491385
A27: Accelerated depreciation (₹) | C27: 0 | D27: =D26*ADRate -> 4600 | E27: =E26*ADRate -> 2760 | F27: =F26*ADRate -> 1656 | G27: =G26*ADRate -> 993.6 | H27: =H26*ADRate -> 596.16 | I27: =I26*ADRate -> 357.696 | J27: =J26*ADRate -> 214.6176 | K27: =K26*ADRate -> 128.77056 | ... AB27: =AB26*ADRate -> 0.021796554
A28: Net cash flow, after tax with accelerated depreciation (₹) | C28: =C23 -> -11478 | D28: =(D20+D21+D22)*(1-TaxRate)+D27*TaxRate -> 2692.2092 | E28: =(E20+E21+E22)*(1-TaxRate)+E27*TaxRate -> 2260.843 | F28: =(F20+F21+F22)*(1-TaxRate)+F27*TaxRate -> 2015.2915 | G28: =(G20+G21+G22)*(1-TaxRate)+G27*TaxRate -> 1881.4591 | H28: =(H20+H21+H22)*(1-TaxRate)+H27*TaxRate -> 1814.89 | I28: =(I20+I21+I22)*(1-TaxRate)+I27*TaxRate -> 1788.9122 | J28: =(J20+J21+J22)*(1-TaxRate)+J27*TaxRate -> 1787.524 | K28: =(K20+K21+K22)*(1-TaxRate)+K27*TaxRate -> 1801.1253 | ... AB28: =(AB20+AB21+AB22)*(1-TaxRate)+AB27*TaxRate -> 0.0054861927 | AC28: =SUMPRODUCT(C28:AB28,C$16:AB$16) -> 5543.4571
A30: Results per m² of walkway
A31: Year-1 electricity bill saved (₹ / m²) | B31: =D20 -> 2208
A32: Year-1 generation (kWh / m²) | B32: =D18 -> 184
A33: NPV, pre-tax (₹ / m²) | B33: =AC24 -> 8174.3022
A34: IRR, pre-tax | B34: =IFERROR(IRR(C24:AB24),"n/a") -> 0.18847795
A35: IRR, after tax with 40% accelerated depreciation | B35: =IFERROR(IRR(C28:AB28),"n/a") -> 0.17026592
A36: Simple payback (years) | B36: =IF(COUNTIF(D25:AB25,"<0")>=25,"> 25",COUNTIF(D25:AB25,"<0")+(-INDEX(C25:AB25,COUNTIF(D25:AB25,"<0")+1))/INDEX(C24:AB24,COUNTIF(D25:AB25,"<0")+2)) -> 5.3495034
A37: Levelised cost of the walkway's power (₹ / kWh) | B37: =(WkSolarPart-AC21-AC22)/AC18 -> 9.1978024
A38: Lifetime generation (kWh / m²) | B38: =SUM(C18:AB18) -> 3445.2592
A40: Both sites side by side (simple payback on year-1 figures)
A41: Site | B41: Year-1 saving net of O&M (₹ / m²) | C41: Simple payback (yrs)
A42: Jamnagar | B42: =WkKWp*WkYieldJam*WkYieldMult*TariffJam-WkOM -> 1410 | C42: =WkInc/B42 -> 8.1404255
A43: Navi Mumbai | B43: =WkKWp*WkYieldMum*WkYieldMult*TariffMum-WkOM -> 2058 | C43: =WkInc/B43 -> 5.5772595
A45: Cost per kWp compared
A46: GridMats Solar Walkway, solar part (₹ / kWp) | B46: =WkPerKWp -> 71875
A47: C&I rooftop solar (₹ / kWp) | B47: =RooftopCost -> 40000
A48: Solar carport (₹ / kWp) | B48: =CarportCost -> 50000
A49: A walkway kWp costs more than a rooftop kWp. It earns its place where roofs are full or shaded and a walkway is needed anyway: it uses no extra land, roof or mounting.
A51: Pilot: GridMats Solar Walkway at the chosen site
A52: Area (m²) | B52: =PilotWalk -> 50
A53: Rated power (kWp) | B53: =PilotWalk*WkKWp -> 8
A54: Year-1 generation (kWh) | B54: =PilotWalk*Wk_Gen1 -> 9200
A55: Year-1 electricity bill saved (₹) | B55: =PilotWalk*Wk_Save1 -> 110400
A56: Installed cost before GridMats co-funding (₹) | B56: =PilotWalk*WkTotal -> 628900

Sheet Sustainability
A1: Sustainability impact
A2: Per solar block (default 100 MWp) over 25 years, and for the proposed pilot.
A4: Measure | B4: Per block | C4: Pilot | D4: Basis
A5: Recycled polypropylene put to use (t) | B5: =Park_PP -> 326.7 | C5: =((PilotMainKm*1000*MainWidth)+(PilotTrackKm*1000*TrackWidth))*PlasticHD/1000+PilotWalk*PlasticLW/1000 -> 33.86 | D5: 6.6 kg/m² OC-HD 40; 4.0 kg/m² OC-LW 40
A6: CO2e avoided: plastic reuse and paving materials (t) | B6: ='Solar Park 100MW'!AC29 -> 904.185 | C6: =((PilotMainKm*1000*MainWidth)+(PilotTrackKm*1000*TrackWidth))*PlasticHD*PPCredit/1000+(PilotMainKm*1000*MainWidth)*IF(MainBaseline="PQC",(PQC_Cement-S1_Cement)*CementEF,BT_Binder*BitumenEF+BT_Mix*HotMixEF-S1_Cement*CementEF)/1000 -> 61.302 | D6: Recycled-PP credit 1.2 kg/kg; bitumen or cement avoided on main roads, incl. BC renewals (block)
A7: CO2e avoided: extra renewable energy (t) | B7: ='Solar Park 100MW'!AC30 -> 9968.8246 | C7: =PW_kWh*WkLife*GridEF/1000 -> 130.64 | D7: Block: cleaner modules × grid factor. Pilot: walkway generation over its life
A8: Total CO2e avoided (t) | B8: =B6+B7 -> 10873.01 | C8: =C6+C7 -> 191.942
A9: Extra clean energy (MWh) | B9: =Park_MWh -> 14040.598 | C9: =PW_kWh*WkLife/1000 -> 184 | D9: Block: 25 years. Pilot walkway: over its life
A10: Dust-suppression water avoided (kL) | B10: =TrackArea*DustWater*DustDays*DustYears*DustCutS2/1000 -> 8820 | C10: =(PilotTrackKm*1000*TrackWidth)*DustWater*DustDays*DustYears*DustCutS2/1000 -> 756 | D10: Construction years only
A11: Rain returned to the ground every year (m³) | B11: =TrackArea*Rainfall/1000*Infiltr -> 11340 | C11: =(PilotTrackKm*1000*TrackWidth)*Rainfall/1000*Infiltr -> 972 | D11: Permeable S2 tracks
A12: Cement avoided if main roads would otherwise be concrete (t) | B12: =MainArea*(PQC_Cement-S1_Cement)/1000 -> 1553.4 | C12: =(PilotMainKm*1000*MainWidth)*(PQC_Cement-S1_Cement)/1000 -> 207.12 | D12: PQC 220 + DLC 150 ≈ 90 kg cement/m²; S1 uses 3.7 kg/m²
A15: Circularity: GridMats grids are 100% post-consumer recycled polypropylene, and can be lifted, reused or recycled at end of life. They work alongside Reliance's own ReRoute plastic-in-bitumen roads: ReRoute for bituminous highways, GridMats where a road must be permeable, fast or cement-free.

Sheet Pilot Offer
A1: Pilot offer to Reliance: scope, value and price
A2: Ex-GST. List = GridMats standard price and terms. Offer = proposed pilot price. Civil works are by Reliance's EPC at its own rates.
A4: Item | B4: Qty | C4: Unit | D4: List rate (₹) | E4: List value (₹) | F4: Offer rate (₹) | G4: Offer value (₹) | H4: Notes
A5: A. Solar-park road pilot: 1 km with control sections
A6: GridMats OC-HD 40, main road S1 (0.4 km × 6 m) | B6: =PilotMainKm*1000*MainWidth -> 2400 | C6: m² | D6: =ListHD -> 935 | E6: =B6*D6 -> 2244000 | F6: =OfferHD -> 900 | G6: =B6*F6 -> 2160000 | H6: Annual-contract rate at pilot size
A7: GridMats OC-HD 40, O&M track S2 (0.6 km × 4.5 m) | B7: =PilotTrackKm*1000*TrackWidth -> 2700 | C7: m² | D7: =ListHD -> 935 | E7: =B7*D7 -> 2524500 | F7: =OfferHD -> 900 | G7: =B7*F7 -> 2430000
A8: Geotextile 200 gsm | B8: =B6+B7 -> 5100 | C8: m² | D8: =Geotex -> 55 | E8: =B8*D8 -> 280500 | F8: =Geotex -> 55 | G8: =B8*F8 -> 280500
A9: U-nails | B9: =ROUNDUP((B6+B7)*NailDensity,0) -> 2040 | C9: nos | D9: =NailPrice -> 8 | E9: =B9*D9 -> 16320 | F9: =NailPrice -> 8 | G9: =B9*F9 -> 16320
A10: Freight to site | B10: =B6+B7 -> 5100 | C10: m² | D10: =Freight -> 60 | E10: =B10*D10 -> 306000 | F10: =Freight -> 60 | G10: =B10*F10 -> 306000 | H10: At cost
A11: Site design (IITPAVE on measured CBR), BoQ, method statement, hold-point QC | B11: 1 | C11: lot | D11: =DesignValue -> 150000 | E11: =B11*D11 -> 150000 | F11: 0 | G11: =B11*F11 -> 0 | H11: Included
A12: On-site GridMats supervisor for the whole build | B12: =ROUNDUP((B6+B7)/LayRate,0) -> 15 | C12: days | D12: =ManDay -> 15000 | E12: =B12*D12 -> 225000 | F12: 0 | G12: =B12*F12 -> 0 | H12: Standard is up to 3 days
A13: Supervisor travel and stay | B13: 1 | C13: lot | D13: =TravelValue -> 75000 | E13: =B13*D13 -> 75000 | F13: 0 | G13: =B13*F13 -> 0 | H13: Normally paid by the client
A14: B. GridMats Solar Walkway demonstrator
A15: GridMats base, OC-LW 40 on open-graded GSB | B15: =PilotWalk -> 50 | C15: m² | D15: =WkBase -> 1078 | E15: =B15*D15 -> 53900 | F15: =WkBase -> 1078 | G15: =B15*F15 -> 53900
A16: Walkable PV layer + inverter, cabling, metering | B16: =PilotWalk -> 50 | C16: m² | D16: =SolarLayer+BOS*PowerDens/1000 -> 11500 | E16: =B16*D16 -> 575000 | F16: =(SolarLayer+BOS*PowerDens/1000)*(1-CoFund) -> 5750 | G16: =B16*F16 -> 287500 | H16: GridMats co-funds the PV part
A17: C. Measurement
A18: IoT sensors, live dashboard, soiling study, 6- and 12-month joint reports | B18: 1 | C18: lot | D18: =MonitorValue -> 400000 | E18: =B18*D18 -> 400000 | F18: 0 | G18: =B18*F18 -> 0 | H18: Free
A19: Total GridMats scope | E19: =SUM(E5:E18) -> 6850220 | G19: =SUM(G5:G18) -> 5534220
A21: What it means for Reliance
A22: Reliance pays GridMats (ex-GST) | G22: =Pilot_Offer -> 5534220
A23: GridMats contribution (list value − offer) | G23: =Pilot_List-Pilot_Offer -> 1316000
A24: Saving on list value | G24: =Pilot_Contrib/Pilot_List -> 0.19211062
A25: Grid price reduction vs the 2025 Kutch trial (₹1,165/m²) | G25: =1-OfferHD/TrialPrice -> 0.22746781
A26: Civil works by Reliance's EPC, indicative (base layers, infill, labour, edges) | G26: =(PilotMainKm*1000*MainWidth)*(S1_Capex-GridHD-Geotex-Freight-NailDensity*NailPrice)+(PilotTrackKm*1000*TrackWidth)*(S2_Capex-GridHD-Geotex-Freight-NailDensity*NailPrice)+PilotWalk*(WkBase-GridLWSmall-Freight) -> 4233710
A27: Total pilot budget for Reliance (GridMats scope + civil) | G27: =Pilot_Pays+Pilot_Civil -> 9767930
A28: Pilot road area (m²) | G28: =(PilotMainKm*1000*MainWidth)+(PilotTrackKm*1000*TrackWidth) -> 5100
A29: Grid laid in (crew-days) | G29: =ROUNDUP(Pilot_RoadArea/LayRate,0) -> 15
A30: Credit against the first order of 25,000 m² or more | G30: =PilotCredit*(G6+G7) -> 459000
A31: Net pilot cost to Reliance after that credit (GridMats scope) | G31: =Pilot_Pays-Pilot_Credit -> 5075220
A32: Rate held for a 12-month park rate contract (₹ / m² OC-HD 40) | G32: =OfferHD -> 900
A33: Net 25-yr saving of the pilot road itself vs conventional (₹, PV) | G33: =(PilotMainKm*1000*MainWidth)*IF(MainBaseline="PQC",Save_S1_PQC,Save_S1_BT)+(PilotTrackKm*1000*TrackWidth)*Save_S2_WBM -> 2772070
A35: Success measures (12 months, measured jointly)
A36: Rut depth | B36: ≤ 10 mm (investigate base if > 20 mm)
A37: Exposed cell tops | B37: ≤ 5% of area
A38: Drainage | B38: No standing water 1 hour after rain
A39: Cracks | B39: None crossing more than 3 cells
A40: Road dust | B40: Dust deposition next to GridMats vs WBM control section
A41: Module soiling | B41: Soiling ratio of rows 10-40 m from GridMats vs WBM control
A42: Upkeep | B42: Maintenance events and cost vs control sections
A43: Solar walkway | B43: Measured W/m², kWh per m² per day, module temperature, slip resistance, uptime

Sheet Scale-up
A1: Scale-up: what the pilot unlocks
A2: Base on Solar Park results. Kutch: >40 billion kWh a year implies about 18-20 GW of solar.
A4: Measure | B4: Block | C4: 1 GW | D4: 5 GW | E4: 20 GW | F4: Note
A5: Solar capacity (MW) | B5: =BlockMWp -> 100 | C5: 1000 | D5: 5000 | E5: 20000
A6: Internal road (km) | B6: =B$5/100*RoadKm -> 10 | C6: =C$5/100*RoadKm -> 100 | D6: =D$5/100*RoadKm -> 500 | E6: =E$5/100*RoadKm -> 2000
A7: GridMats area (m²) | B7: =B$5/BlockMWp*ParkArea -> 49500 | C7: =C$5/BlockMWp*ParkArea -> 495000 | D7: =D$5/BlockMWp*ParkArea -> 2475000 | E7: =E$5/BlockMWp*ParkArea -> 9900000
A8: Up-front GridMats premium (₹ Cr) | B8: =B$5/BlockMWp*Park_Premium -> 3.459285 | C8: =C$5/BlockMWp*Park_Premium -> 34.59285 | D8: =D$5/BlockMWp*Park_Premium -> 172.96425 | E8: =E$5/BlockMWp*Park_Premium -> 691.857
A9: NPV to Reliance over 25 years (₹ Cr) | B9: =B$5/BlockMWp*Park_NPV -> 4.0949028 | C9: =C$5/BlockMWp*Park_NPV -> 40.949028 | D9: =D$5/BlockMWp*Park_NPV -> 204.74514 | E9: =E$5/BlockMWp*Park_NPV -> 818.98057
A10: Road upkeep avoided, undiscounted (₹ Cr) | B10: =B$5/BlockMWp*Park_UpkeepNom -> 19.343599 | C10: =C$5/BlockMWp*Park_UpkeepNom -> 193.43599 | D10: =D$5/BlockMWp*Park_UpkeepNom -> 967.17995 | E10: =E$5/BlockMWp*Park_UpkeepNom -> 3868.7198
A11: Extra clean energy over 25 years (GWh) | B11: =B$5/BlockMWp*Park_MWh/1000 -> 14.040598 | C11: =C$5/BlockMWp*Park_MWh/1000 -> 140.40598 | D11: =D$5/BlockMWp*Park_MWh/1000 -> 702.0299 | E11: =E$5/BlockMWp*Park_MWh/1000 -> 2808.1196
A12: Recycled PP put to use (t) | B12: =B$5/BlockMWp*Park_PP -> 326.7 | C12: =C$5/BlockMWp*Park_PP -> 3267 | D12: =D$5/BlockMWp*Park_PP -> 16335 | E12: =E$5/BlockMWp*Park_PP -> 65340
A13: CO2e avoided over 25 years (t) | B13: =B$5/BlockMWp*Park_CO2 -> 10873.01 | C13: =C$5/BlockMWp*Park_CO2 -> 108730.1 | D13: =D$5/BlockMWp*Park_CO2 -> 543650.48 | E13: =E$5/BlockMWp*Park_CO2 -> 2174601.9
A14: 40-ft containers of grid | B14: =ROUNDUP(B$5/BlockMWp*ParkArea/ContainerM2,0) -> 45 | C14: =ROUNDUP(C$5/BlockMWp*ParkArea/ContainerM2,0) -> 450 | D14: =ROUNDUP(D$5/BlockMWp*ParkArea/ContainerM2,0) -> 2250 | E14: =ROUNDUP(E$5/BlockMWp*ParkArea/ContainerM2,0) -> 9000
A17: Solar walkways across Reliance sites (illustrative, year 1)
A18: Case | B18: Area (m²) | C18: Rated MWp | D18: MWh / yr | E18: ₹ Cr / yr saved | F18: Basis
A19: Jamnagar Giga Complex and data-centre campus walkways | B19: 10000 | C19: =B19*WkKWp/1000 -> 1.6 | D19: =B19*WkKWp*WkYieldJam*WkYieldMult/1000 -> 2080 | E19: =D19*1000*TariffJam/10000000 -> 1.56 | F19: Jamnagar yield and tariff
A20: Reliance Corporate Park and Jio World Centre walkways, Mumbai | B20: 5000 | C20: =B20*WkKWp/1000 -> 0.8 | D20: =B20*WkKWp*WkYieldMum*WkYieldMult/1000 -> 920 | E20: =D20*1000*TariffMum/10000000 -> 1.104 | F20: Mumbai yield and tariff
A21: Jio-bp EV-charging hubs: 500 sites × 40 m² | B21: 20000 | C21: =B21*WkKWp/1000 -> 3.2 | D21: =B21*WkKWp*WkYieldJam*WkYieldMult/1000 -> 4160 | E21: =D21*1000*TariffJam/10000000 -> 3.12 | F21: Jamnagar basis, for scale only
A22: Total | B22: =SUM(B19:B21) -> 35000 | C22: =SUM(C19:C21) -> 5.6 | D22: =SUM(D19:D21) -> 7160 | E22: =SUM(E19:E21) -> 5.784

Sheet Sensitivity
A1: Sensitivity: NPV per solar block (₹ Cr, 25 years)
A2: Each row changes one driver and keeps everything else at the selected scenario. Low and high values can be edited.
A4: NPV at selected scenario (₹ Cr) | D4: =Park_NPV -> 4.0949028
A6: Driver | B6: Low value | C6: High value | D6: NPV at low | E6: NPV at high | F6: Swing | G6: How it is computed
A7: GridMats grid price (± 10%) | B7: -0.1 | C7: 0.1 | D7: =D$4-B7*GridHD*ParkArea*(1+GM_RoutinePct*U_PVF)/10000000 -> 4.5725602 | E7: =D$4-C7*GridHD*ParkArea*(1+GM_RoutinePct*U_PVF)/10000000 -> 3.6172455 | F7: =ABS(E7-D7) -> 0.95531466 | G7: Build cost and the 0.5%/yr upkeep linked to it
A8: WBM upkeep (− / + 50%) | B8: -0.5 | C8: 0.5 | D8: =D$4+B8*TrackArea*Upk_WBM/10000000 -> 1.6701502 | E8: =D$4+C8*TrackArea*Upk_WBM/10000000 -> 6.5196555 | F8: =ABS(E8-D8) -> 4.8495054 | G8: Scales PV of WBM upkeep avoided
A9: Bituminous upkeep (− / + 50%) | B9: -0.5 | C9: 0.5 | D9: =D$4+B9*MainArea*Upk_BT/10000000*(MainBaseline<>"PQC") -> 2.898461 | E9: =D$4+C9*MainArea*Upk_BT/10000000*(MainBaseline<>"PQC") -> 5.2913446 | F9: =ABS(E9-D9) -> 2.3928836 | G9: Only when main roads would be bituminous
A10: GridMats upkeep (+ / − 50%) | B10: 0.5 | C10: -0.5 | D10: =D$4-B10*(MainArea*Upk_S1+TrackArea*Upk_S2)/10000000 -> 3.3202186 | E10: =D$4-C10*(MainArea*Upk_S1+TrackArea*Upk_S2)/10000000 -> 4.8695871 | F10: =ABS(E10-D10) -> 1.5493685 | G10: Scales PV of GridMats upkeep
A11: Share of soiling from track dust | B11: 0.05 | C11: 0.3 | D11: =D$4+(B11-DustShare)*(U_Energy*EnergyValue+U_CarbEn*CarbonPrice) -> 2.8893248 | E11: =D$4+(C11-DustShare)*(U_Energy*EnergyValue+U_CarbEn*CarbonPrice) -> 5.9032699 | F11: =ABS(E11-D11) -> 3.0139452 | G11: Linear in the energy and energy-carbon terms
A12: Value of extra energy (₹ / kWh) | B12: 2.4 | C12: 3.5 | D12: =D$4+(B12-EnergyValue)*(U_Energy*DustShare+U_Early*DaysEarly) -> 3.9391721 | E12: =D$4+(C12-EnergyValue)*(U_Energy*DustShare+U_Early*DaysEarly) -> 4.5101848 | F12: =ABS(E12-D12) -> 0.57101276 | G12: Linear
A13: Carbon value (₹ / t CO2e) | B13: 0 | C13: 1500 | D13: =D$4+(B13-CarbonPrice)*(U_CarbMat+U_CarbEn*DustShare) -> 3.6353123 | E13: =D$4+(C13-CarbonPrice)*(U_CarbMat+U_CarbEn*DustShare) -> 4.6201492 | F13: =ABS(E13-D13) -> 0.98483694 | G13: Linear
A14: Road length per 100 MW (km) | B14: 8 | C14: 12 | D14: =D$4+(B14/RoadKm-1)*(U_Road+U_CarbMat*CarbonPrice) -> 3.6375957 | E14: =D$4+(C14/RoadKm-1)*(U_Road+U_CarbMat*CarbonPrice) -> 4.55221 | F14: =ABS(E14-D14) -> 0.9146143 | G14: Road terms scale with length
A15: Discount rate | B15: 0.08 | C15: 0.12 | D15: =Park_NPV8 -> 5.7078719 | E15: =Park_NPV12 -> 2.8789415 | F15: =ABS(E15-D15) -> 2.8289304 | G15: Full recomputation (8% and 12% fixed)
A18: Scenarios side by side
A19: Measure | B19: Conservative | C19: Base | D19: Optimistic
A20: Share of soiling from track dust | B20: =Inputs!$D$29 -> 0.1 | C20: =Inputs!$E$29 -> 0.15 | D20: =Inputs!$F$29 -> 0.25
A21: Value of extra energy (₹ / kWh) | B21: =Inputs!$D$21 -> 2.55 | C21: =Inputs!$E$21 -> 2.7 | D21: =Inputs!$F$21 -> 2.9
A22: Cleaning cost avoided | B22: =Inputs!$D$32 -> 0 | C22: =Inputs!$E$32 -> 0 | D22: =Inputs!$F$32 -> 0.05
A23: Earlier energisation (days) | B23: =Inputs!$D$33 -> 0 | C23: =Inputs!$E$33 -> 0 | D23: =Inputs!$F$33 -> 2
A24: Carbon value (₹ / t) | B24: =Inputs!$D$12 -> 400 | C24: =Inputs!$E$12 -> 700 | D24: =Inputs!$F$12 -> 1500
A25: NPV per block (₹ Cr) | B25: =U_Road+U_Energy*B20*B21+U_Clean*B22+U_Early*B23*B21+U_CarbMat*B24+U_CarbEn*B20*B24 -> 3.3013491 | C25: =U_Road+U_Energy*C20*C21+U_Clean*C22+U_Early*C23*C21+U_CarbMat*C24+U_CarbEn*C20*C24 -> 4.0949028 | D25: =U_Road+U_Energy*D20*D21+U_Clean*D22+U_Early*D23*D21+U_CarbMat*D24+U_CarbEn*D20*D24 -> 7.6615724
A26: NPV per block if the energy benefit is zero (roads only) (₹ Cr) | C26: =U_Road+U_CarbMat*CarbonPrice -> 2.2865357
A28: Note: the conservative case still includes avoided WBM and bitumen upkeep. With no energy benefit at all, the roads-only line shows the NPV from upkeep and carbon alone.

Sheet Sources
A1: Sources
A2: Public sources accessed Sep-Oct 2026; GridMats documents current at 7 Oct 2026.
A4: # | B4: Source | C4: Used for
A5: 1 | B5: GridMats master data and price ladder (Rev 1.3, 25-26 Sep 2026) | C5: Grid prices, panel weights, recycled PP per m², approved product claims
A6: 2 | B6: GridMats Sales Pitch 2026 (Rev 1.5) | C6: Indicative installed costs, conventional comparators, cement and CO2 per 1,000 m²
A7: 3 | B7: GridMats Systems Manual and specification clauses (Rev 1.3, Oct 2026) | C7: Base tables by load class and CBR, upkeep thresholds, laying rate
A8: 4 | B8: GridMats Design Engine 73: technical deck, commercial deck, BoQ and sample proposal | C8: Unit rates, lifecycle method, emission factors, cross-sections
A9: 5 | B9: GridMats solar and wind parks flier (Oct 2026) | C9: 8-12 km of road per 100 MW, per-km park rate, system choice by road type
A10: 6 | B10: GridMats Solar Walkway flier (6 Oct 2026) and GridMats Solar pilot quote (Oct 2026) | C10: 160 W/m², construction, pilot method, ₹9,500/m²
A11: 7 | B11: Reliance purchase and work orders, Kutch Z2 block trial (Sep 2025) and GridMats IITPAVE design (Aug 2025) | C11: 2025 price, quantities, cross-section on CBR 3-5% saline ground
A12: 8 | B12: Bureau Veritas BVIPL:SPL:BL/2545/7/2021/A; IIT Hyderabad interim report (Oct 2025) | C12: 407 t/m² lab test on the empty OC-HD 40 panel; 2.0× base modulus at CBR 5%
A13: 9 | B13: Reliance AGM 2026 coverage (BusinessToday, 19 Jun 2026); RIL Annual Report 2025-26; PL Capital Q1 FY27 note | C13: Kutch 5.5 lakh acres, >40 billion kWh/yr, 55 MWp/day peak; 100 GW by 2030; Net Carbon Zero 2035
A14: 10 | B14: CEA CO2 Baseline Database v21.0 (FY2024-25) | C14: Grid emission factor 0.710 t/MWh
A15: 11 | B15: GERC tariff orders FY2026-27 (25 Mar 2026); MERC Case 75 of 2025 | C15: Gujarat and Maharashtra HT tariffs
A16: 12 | B16: SECI ISTS-XX auction (Oct 2025); NHPC / NTPC solar tenders | C16: Solar PPA levels ₹2.52-2.87/kWh
... A21: 17 | B21: Greentechlead (2026), Bridgeway Power (2026), studiomatrx (2026) | C21: Solar capex, rooftop and carport costs
B23: Figures marked 'Assumption' on the Inputs sheet are GridMats estimates for this model. The pilot is designed to measure the uncertain ones (soiling, dust, walkway yield).
